Workbook

Sheet Cover
A1: ServiceNow, Inc. (NOW) - DCF Valuation Workbook
A3: Investment snapshot
A4: Company | B4: ServiceNow, Inc. (NOW) | D4: Valuation story
A5: Valuation date | B5: 2026-07-23 | D5: Base value: $112.47, 15.5% above the $97.35 market snapshot.
A6: Model status | B6: screen-grade | D6: What spot implies: about 14.5% annual revenue growth if SBC-adjusted EBIT margin reaches 26%.
A7: Current / implied value per share | B7: =TEXT('Executive Summary'!B10,"$#,##0.00")&" / "&TEXT('Executive Summary'!B9,"$#,##0.00") -> $97.35 / $112.47 | D7: Base variant: 17.6% revenue CAGR and SBC-adjusted EBIT margin rising from 16.5% to 26%.
A8: Base-case upside / downside | B8: =TEXT('Executive Summary'!B11,"0.0%") -> 15.5% | D8: Proof: cRPO holds near 20%, the 2030 subscription target stays credible, and SBC falls below 10% of revenue.
A9: WACC / terminal growth | B9: =TEXT('Control Panel'!B78,"0.0%")&" / "&TEXT('Control Panel'!B83,"0.0%") -> 8.6% / 3.0% | D9: Break: growth falls below the market-implied path before margin expansion; downside value is $65.09.
D10: Posture: watchlist / starter only. Terminal value is 79% of enterprise value, so duration risk remains high.
A12: Navigation
A13: Executive Summary | B13: =HYPERLINK("#'Executive Summary'!A1","Open Executive Summary") -> Open Executive Summary
A14: Control Panel | B14: =HYPERLINK("#'Control Panel'!A1","Open Control Panel") -> Open Control Panel
A15: Historical Financials | B15: =HYPERLINK("#'Historical Financials'!A1","Open Historical Financials") -> Open Historical Financials
A16: Revenue Build | B16: =HYPERLINK("#'Revenue Build'!A1","Open Revenue Build") -> Open Revenue Build
A17: Margin Cost Build | B17: =HYPERLINK("#'Margin Cost Build'!A1","Open Margin Cost Build") -> Open Margin Cost Build
A18: Working Capital | B18: =HYPERLINK("#'Working Capital'!A1","Open Working Capital") -> Open Working Capital
A19: Capex D&A | B19: =HYPERLINK("#'Capex D&A'!A1","Open Capex D&A") -> Open Capex D&A
A20: Tax Schedule | B20: =HYPERLINK("#'Tax Schedule'!A1","Open Tax Schedule") -> Open Tax Schedule
A21: Unlevered FCF | B21: =HYPERLINK("#'Unlevered FCF'!A1","Open Unlevered FCF") -> Open Unlevered FCF
A22: WACC | B22: =HYPERLINK("#'WACC'!A1","Open WACC") -> Open WACC
A23: Terminal Value | B23: =HYPERLINK("#'Terminal Value'!A1","Open Terminal Value") -> Open Terminal Value
A24: DCF Valuation | B24: =HYPERLINK("#'DCF Valuation'!A1","Open DCF Valuation") -> Open DCF Valuation
A25: Sensitivities | B25: =HYPERLINK("#'Sensitivities'!A1","Open Sensitivities") -> Open Sensitivities
A26: Checks | B26: =HYPERLINK("#'Checks'!A1","Open Checks") -> Open Checks
A27: Source Notes | B27: =HYPERLINK("#'Source Notes'!A1","Open Source Notes") -> Open Source Notes
A31: Key diligence warnings
A32: History coverage | B32: Only source-backed historical periods are shown; unavailable history is intentionally blank.
A33: Operating drivers | B33: Use sector-relevant KPI drivers where material; read Source Notes for disclosed proxies.
A34: Model checks | B34: Review Checks and Source Notes before using model outputs.
A35: Readiness | B35: screen-grade

Sheet Executive Summary
A1: Executive Summary
A3: Posture warning | B3: Screen-grade only; open assumptions or evidence gaps remain.
A4: Company name | B4: ='Control Panel'!$B$4 -> ServiceNow, Inc.
A5: Valuation date | B5: ='Control Panel'!$B$7 -> 2026-07-23
A6: Currency / units | B6: ='Control Panel'!$B$5&" / "&'Control Panel'!$B$6 -> USD / $mm except per-share data
A7: Enterprise value | B7: ='DCF Valuation'!$B$6 -> 117103.74
A8: Equity value | B8: ='DCF Valuation'!$B$16 -> 116293.74
A9: Implied share price | B9: ='DCF Valuation'!$B$18 -> 112.46977
A10: Current share price | B10: ='DCF Valuation'!$B$19 -> 97.35
A11: Upside / downside | B11: ='DCF Valuation'!$B$20 -> 0.15531353
A12: Base case implied valuation | B12: =Sensitivities!G$51 -> 112.46977
A13: Downside case valuation | B13: =Sensitivities!G$50 -> 65.091441
A14: Upside case valuation | B14: =Sensitivities!G$52 -> 147.69919
A15: Recommendation placeholder | B15: ='Control Panel'!$B$13 -> Screen-grade only; open assumptions or evidence gaps remain.
A18: Key value drivers
A19: Forecast revenue CAGR | B19: =(('Revenue Build'!J$14/'Revenue Build'!D$14)^(1/6))-1 -> 0.17635689
A20: Terminal EBITDA margin | B20: ='Margin Cost Build'!J$11 -> 0.31
A21: Selected WACC | B21: ='Control Panel'!$B$78 -> 0.0862765
A22: Terminal growth rate | B22: ='Control Panel'!$B$83 -> 0.03
A23: Terminal value % of EV | B23: ='DCF Valuation'!$B$7 -> 0.79387633
A26: Main risks and open diligence
A27: Risk 1 | B27: Add source-backed multi-year history before relying on trend conclusions.
A28: Risk 2 | B28: Confirm WACC market inputs as of valuation date.
A29: Risk 3 | B29: Validate terminal growth, exit multiple, and terminal ROIC support.
A30: Risk 4 | B30: Review NOLs, SBC, leases, pensions, minorities, and debt-like items where material.

Sheet Control Panel
A1: Control Panel
A3: Model identity and switches
A4: Company name | B4: ServiceNow, Inc.
A5: Currency | B5: USD
A6: Units | B6: $mm except per-share data
A7: Valuation date | B7: 2026-07-23
A8: Model status | B8: screen-grade
A9: Workbook mode | B9: banker_formula_workbook
A10: Scenario selection | B10: Base
A11: Mid-year convention | B11: No
A12: Current share price | B12: 97.35
A13: Recommendation placeholder | B13: Screen-grade only; open assumptions or evidence gaps remain.
A14: Selected terminal value method | B14: Gordon Growth
A15: Other revenue growth factor | B15: 0
A16: Gross profit bridge / revenue | B16: 0.345
A17: Scenario assumptions
A18: Case / metric | B18: 2026E | C18: 2027E | D18: 2028E | E18: 2029E | F18: 2030E | G18: 2031E
A20: Revenue growth assumptions
A21: Base | B21: 0.2208 | C21: 0.2 | D21: 0.19 | E21: 0.17 | F21: 0.16 | G21: 0.12
A22: Downside | B22: 0.2208 | C22: 0.17 | D22: 0.14 | E22: 0.11 | F22: 0.08 | G22: 0.06
A23: Upside | B23: 0.2208 | C23: 0.22 | D23: 0.21 | E23: 0.19 | F23: 0.17 | G23: 0.15
A25: EBITDA margin assumptions
A26: Base | B26: 0.215 | C26: 0.23 | D26: 0.25 | E26: 0.27 | F26: 0.29 | G26: 0.31
A27: Downside | B27: 0.215 | C27: 0.21 | D27: 0.22 | E27: 0.23 | F27: 0.24 | G27: 0.25
A28: Upside | B28: 0.215 | C28: 0.25 | D28: 0.28 | E28: 0.31 | F28: 0.34 | G28: 0.36
A30: EBIT margin reference assumptions
A31: Base | B31: 0.165 | C31: 0.18 | D31: 0.2 | E31: 0.22 | F31: 0.24 | G31: 0.26
A32: Downside | B32: 0.165 | C32: 0.16 | D32: 0.17 | E32: 0.18 | F32: 0.19 | G32: 0.2
A33: Upside | B33: 0.165 | C33: 0.2 | D33: 0.23 | E33: 0.26 | F33: 0.29 | G33: 0.31
A35: D&A % revenue assumptions
A36: Base | B36: 0.05 | C36: 0.05 | D36: 0.05 | E36: 0.05 | F36: 0.05 | G36: 0.05
A37: Downside | B37: 0.05 | C37: 0.05 | D37: 0.05 | E37: 0.05 | F37: 0.05 | G37: 0.05
A38: Upside | B38: 0.05 | C38: 0.05 | D38: 0.05 | E38: 0.05 | F38: 0.05 | G38: 0.05
A40: Capex % revenue assumptions
A41: Base | B41: 0.06 | C41: 0.06 | D41: 0.06 | E41: 0.06 | F41: 0.06 | G41: 0.06
A42: Downside | B42: 0.06 | C42: 0.06 | D42: 0.06 | E42: 0.06 | F42: 0.06 | G42: 0.06
A43: Upside | B43: 0.06 | C43: 0.06 | D43: 0.06 | E43: 0.06 | F43: 0.06 | G43: 0.06
A45: Operating NWC % revenue assumptions
A46: Base | B46: -0.39 | C46: -0.39 | D46: -0.39 | E46: -0.39 | F46: -0.39 | G46: -0.39
A47: Downside | B47: -0.39 | C47: -0.36 | D47: -0.36 | E47: -0.36 | F47: -0.36 | G47: -0.36
A48: Upside | B48: -0.39 | C48: -0.42 | D48: -0.42 | E48: -0.42 | F48: -0.42 | G48: -0.42
A50: Book tax rate assumptions
A51: Base | B51: 0.21 | C51: 0.21 | D51: 0.21 | E51: 0.21 | F51: 0.21 | G51: 0.21
A52: Downside | B52: 0.21 | C52: 0.21 | D52: 0.21 | E52: 0.21 | F52: 0.21 | G52: 0.21
A53: Upside | B53: 0.21 | C53: 0.21 | D53: 0.21 | E53: 0.21 | F53: 0.21 | G53: 0.21
A55: Cash tax rate assumptions
A56: Base | B56: 0.21 | C56: 0.21 | D56: 0.21 | E56: 0.21 | F56: 0.21 | G56: 0.21
A57: Downside | B57: 0.21 | C57: 0.21 | D57: 0.21 | E57: 0.21 | F57: 0.21 | G57: 0.21
A58: Upside | B58: 0.21 | C58: 0.21 | D58: 0.21 | E58: 0.21 | F58: 0.21 | G58: 0.21
A60: Working-capital driver assumptions
A61: AR % revenue | B61: -0.39 | C61: -0.39 | D61: -0.39 | E61: -0.39 | F61: -0.39 | G61: -0.39
A62: Inventory % revenue | B62: 0 | C62: 0 | D62: 0 | E62: 0 | F62: 0 | G62: 0
A63: AP % revenue | B63: 0 | C63: 0 | D63: 0 | E63: 0 | F63: 0 | G63: 0
A64: Other current assets % revenue | B64: 0 | C64: 0 | D64: 0 | E64: 0 | F64: 0 | G64: 0
A65: Other current liabilities % revenue | B65: 0 | C65: 0 | D65: 0 | E65: 0 | F65: 0 | G65: 0
A68: WACC inputs and selected WACC
A69: Risk-free rate | B69: 0.0463
A70: Beta | B70: 0.96
A71: Market risk premium | B71: 0.045
A72: Size premium | B72: 0
A73: Pre-tax cost of debt | B73: 0.055
A74: Target debt / total capital | B74: 0.07
A75: Target equity / total capital | B75: =1-B74 -> 0.93
A76: Use WACC override? | B76: No
A77: WACC override | B77: 0.0899965
A78: Selected WACC | B78: =IF(B76="Yes",B77,WACC!$B$17) -> 0.0862765
A79: External link status | B79: No external links
A82: Terminal value and EV-to-equity bridge
A83: Terminal growth rate | B83: 0.03
A84: Exit multiple | B84: 15
A85: Net debt | B85: 810
A86: Diluted shares | B86: 1034
A87: Minority interest | B87: 0
A88: Preferred stock | B88: 0
A89: Non-operating assets | B89: 0
A90: Other equity adjustments | B90: 0

Sheet Historical Financials
A1: Historical Financials
A5: Fiscal year | B5: N/A | C5: N/A | D5: 2025A | E5: 2026E | F5: 2027E | G5: 2028E | H5: 2029E | I5: 2030E | J5: 2031E | K5: Source label | L5: Notes
A6: Revenue | D6: 13278 | E6: ='Revenue Build'!E$14 -> 16209.782 | F6: ='Revenue Build'!F$14 -> 19451.739 | G6: ='Revenue Build'!G$14 -> 23147.569 | H6: ='Revenue Build'!H$14 -> 27082.656 | I6: ='Revenue Build'!I$14 -> 31415.881 | J6: ='Revenue Build'!J$14 -> 35185.787 | K6: derived | L6: Latest historical year populated from plan.json; add multi-year sourced history before circulation.
A7: Revenue growth | B7: - | C7: =IFERROR(C6/B6-1,"") | D7: =IFERROR(D6/C6-1,"") | E7: =E6/D6-1 -> 0.2208 | F7: =F6/E6-1 -> 0.2 | G7: =G6/F6-1 -> 0.19 | H7: =H6/G6-1 -> 0.17 | I7: =I6/H6-1 -> 0.16 | J7: =J6/I6-1 -> 0.12 | K7: derived | L7: Formula-derived
A8: Gross profit (not modeled) | D8: 10294.433 | K8: not modeled | L8: Not used in valuation; no cost-of-revenue forecast was modeled.
A9: Gross margin (not modeled) | B9: =IFERROR(B8/B6,"") | C9: =IFERROR(C8/C6,"") | D9: =D8/D6 -> 0.7753 | K9: not modeled | L9: Not used in valuation; no cost-of-revenue forecast was modeled.
A10: EBITDA | D10: 2932 | E10: ='Margin Cost Build'!E$12 -> 3485.1032 | F10: ='Margin Cost Build'!F$12 -> 4473.8999 | G10: ='Margin Cost Build'!G$12 -> 5786.8923 | H10: ='Margin Cost Build'!H$12 -> 7312.3171 | I10: ='Margin Cost Build'!I$12 -> 9110.6055 | J10: ='Margin Cost Build'!J$12 -> 10907.594 | K10: derived | L10: Latest historical year populated from plan.json; add multi-year sourced history before circulation.
A11: EBITDA margin | B11: =IFERROR(B10/B6,"") | C11: =IFERROR(C10/C6,"") | D11: =D10/D6 -> 0.22081639 | E11: =E10/E6 -> 0.215 | F11: =F10/F6 -> 0.23 | G11: =G10/G6 -> 0.25 | H11: =H10/H6 -> 0.27 | I11: =I10/I6 -> 0.29 | J11: =J10/J6 -> 0.31 | K11: derived | L11: Formula-derived
A12: D&A | D12: 738 | E12: ='Capex D&A'!E$12 -> 810.48912 | F12: ='Capex D&A'!F$12 -> 972.58694 | G12: ='Capex D&A'!G$12 -> 1157.3785 | H12: ='Capex D&A'!H$12 -> 1354.1328 | I12: ='Capex D&A'!I$12 -> 1570.7941 | J12: ='Capex D&A'!J$12 -> 1759.2893 | K12: derived | L12: Latest historical year populated from plan.json; add multi-year sourced history before circulation.
A13: EBIT | D13: 2194 | E13: ='Margin Cost Build'!E$15 -> 2674.6141 | F13: ='Margin Cost Build'!F$15 -> 3501.313 | G13: ='Margin Cost Build'!G$15 -> 4629.5139 | H13: ='Margin Cost Build'!H$15 -> 5958.1843 | I13: ='Margin Cost Build'!I$15 -> 7539.8114 | J13: ='Margin Cost Build'!J$15 -> 9148.3045 | K13: derived | L13: Latest historical year populated from plan.json; add multi-year sourced history before circulation.
A14: EBIT margin | B14: =IFERROR(B13/B6,"") | C14: =IFERROR(C13/C6,"") | D14: =D13/D6 -> 0.16523573 | E14: =E13/E6 -> 0.165 | F14: =F13/F6 -> 0.18 | G14: =G13/G6 -> 0.2 | H14: =H13/H6 -> 0.22 | I14: =I13/I6 -> 0.24 | J14: =J13/J6 -> 0.26 | K14: derived | L14: Formula-derived
A15: Taxes | D15: 461 | E15: ='Tax Schedule'!E$12 -> 561.66896 | F15: ='Tax Schedule'!F$12 -> 735.27573 | G15: ='Tax Schedule'!G$12 -> 972.19791 | H15: ='Tax Schedule'!H$12 -> 1251.2187 | I15: ='Tax Schedule'!I$12 -> 1583.3604 | J15: ='Tax Schedule'!J$12 -> 1921.144 | K15: derived | L15: Latest historical year populated from plan.json; add multi-year sourced history before circulation.
A16: Net income | E16: =E13-E15 -> 2112.9451 | F16: =F13-F15 -> 2766.0373 | G16: =G13-G15 -> 3657.3159 | H16: =H13-H15 -> 4706.9656 | I16: =I13-I15 -> 5956.451 | J16: =J13-J15 -> 7227.1606 | K16: not provided | L16: Net income was not supplied for this FCFF historical display.
A17: Capex | D17: 868 | E17: ='Capex D&A'!E$9 -> 972.58694 | F17: ='Capex D&A'!F$9 -> 1167.1043 | G17: ='Capex D&A'!G$9 -> 1388.8542 | H17: ='Capex D&A'!H$9 -> 1624.9594 | I17: ='Capex D&A'!I$9 -> 1884.9529 | J17: ='Capex D&A'!J$9 -> 2111.1472 | K17: derived | L17: Latest historical year populated from plan.json; add multi-year sourced history before circulation.
A18: Operating NWC | D18: -5150 | E18: ='Working Capital'!E$16 -> -6321.8151 | F18: ='Working Capital'!F$16 -> -7586.1782 | G18: ='Working Capital'!G$16 -> -9027.552 | H18: ='Working Capital'!H$16 -> -10562.236 | I18: ='Working Capital'!I$16 -> -12252.194 | J18: ='Working Capital'!J$16 -> -13722.457 | K18: derived | L18: Latest historical year populated from plan.json; add multi-year sourced history before circulation.
A19: Change in NWC | B19: - | C19: =IF(AND(ISNUMBER(B18),ISNUMBER(C18)),C18/C6-B18/B6,"") | D19: =IF(AND(ISNUMBER(C18),ISNUMBER(D18)),D18/D6-C18/C6,"") | E19: ='Working Capital'!E$17 -> -1171.8151 | F19: ='Working Capital'!F$17 -> -1264.363 | G19: ='Working Capital'!G$17 -> -1441.3739 | H19: ='Working Capital'!H$17 -> -1534.6838 | I19: ='Working Capital'!I$17 -> -1689.9577 | J19: ='Working Capital'!J$17 -> -1470.2632 | K19: derived | L19: Formula-derived
A20: Unlevered FCF | D20: 2681 | E20: ='Unlevered FCF'!E$14 -> 3122.6624 | F20: ='Unlevered FCF'!F$14 -> 3835.8829 | G20: ='Unlevered FCF'!G$14 -> 4867.2141 | H20: ='Unlevered FCF'!H$14 -> 5970.8229 | I20: ='Unlevered FCF'!I$14 -> 7332.25 | J20: ='Unlevered FCF'!J$14 -> 8345.566 | K20: derived | L20: Latest historical year populated from plan.json; add multi-year sourced history before circulation.
A21: PP&E | D21: 2289 | E21: ='Capex D&A'!E$13 -> 2451.0978 | F21: ='Capex D&A'!F$13 -> 2645.6152 | G21: ='Capex D&A'!G$13 -> 2877.0909 | H21: ='Capex D&A'!H$13 -> 3147.9175 | I21: ='Capex D&A'!I$13 -> 3462.0763 | J21: ='Capex D&A'!J$13 -> 3813.9341 | K21: derived | L21: Latest historical year populated from plan.json; add multi-year sourced history before circulation.

Sheet Revenue Build
A1: Revenue Build
A5: Fiscal year | B5: N/A | C5: N/A | D5: 2025A | E5: 2026E | F5: 2027E | G5: 2028E | H5: 2029E | I5: 2030E | J5: 2031E
A7: Scenario-linked revenue forecast
A8: Selected scenario | B8: N/A | C8: N/A | D8: Actual | E8: ='Control Panel'!$B$10 -> Base | F8: ='Control Panel'!$B$10 -> Base | G8: ='Control Panel'!$B$10 -> Base | H8: ='Control Panel'!$B$10 -> Base | I8: ='Control Panel'!$B$10 -> Base | J8: ='Control Panel'!$B$10 -> Base
A9: Revenue growth assumption | B9: - | C9: =IFERROR(C14/B14-1,"") | D9: =IFERROR(D14/C14-1,"") | E9: =INDEX('Control Panel'!B$21:B$23,MATCH('Control Panel'!$B$10,'Control Panel'!$A$21:$A$23,0)) -> 0.2208 | F9: =INDEX('Control Panel'!C$21:C$23,MATCH('Control Panel'!$B$10,'Control Panel'!$A$21:$A$23,0)) -> 0.2 | G9: =INDEX('Control Panel'!D$21:D$23,MATCH('Control Panel'!$B$10,'Control Panel'!$A$21:$A$23,0)) -> 0.19 | H9: =INDEX('Control Panel'!E$21:E$23,MATCH('Control Panel'!$B$10,'Control Panel'!$A$21:$A$23,0)) -> 0.17 | I9: =INDEX('Control Panel'!F$21:F$23,MATCH('Control Panel'!$B$10,'Control Panel'!$A$21:$A$23,0)) -> 0.16 | J9: =INDEX('Control Panel'!G$21:G$23,MATCH('Control Panel'!$B$10,'Control Panel'!$A$21:$A$23,0)) -> 0.12
A10: Core revenue | D10: 13278 | E10: =D10*(1+E9) -> 16209.782 | F10: =E10*(1+F9) -> 19451.739 | G10: =F10*(1+G9) -> 23147.569 | H10: =G10*(1+H9) -> 27082.656 | I10: =H10*(1+I9) -> 31415.881 | J10: =I10*(1+J9) -> 35185.787
A11: Other revenue | D11: 0 | E11: =D11*(1+E9*'Control Panel'!$B$15) -> 0 | F11: =E11*(1+F9*'Control Panel'!$B$15) -> 0 | G11: =F11*(1+G9*'Control Panel'!$B$15) -> 0 | H11: =G11*(1+H9*'Control Panel'!$B$15) -> 0 | I11: =H11*(1+I9*'Control Panel'!$B$15) -> 0 | J11: =I11*(1+J9*'Control Panel'!$B$15) -> 0
A12: Segment mix / driver placeholder | B12: =IFERROR(B10/B14,"") | C12: =IFERROR(C10/C14,"") | D12: =D10/D14 -> 1 | E12: =E10/E14 -> 1 | F12: =F10/F14 -> 1 | G12: =G10/G14 -> 1 | H12: =H10/H14 -> 1 | I12: =I10/I14 -> 1 | J12: =J10/J14 -> 1
A14: Output revenue | B14: =SUM(B10:B11) -> 0 | C14: =SUM(C10:C11) -> 0 | D14: =SUM(D10:D11) -> 13278 | E14: =SUM(E10:E11) -> 16209.782 | F14: =SUM(F10:F11) -> 19451.739 | G14: =SUM(G10:G11) -> 23147.569 | H14: =SUM(H10:H11) -> 27082.656 | I14: =SUM(I10:I11) -> 31415.881 | J14: =SUM(J10:J11) -> 35185.787
A15: Output revenue growth | B15: - | C15: =IFERROR(C14/B14-1,"") | D15: =IFERROR(D14/C14-1,"") | E15: =E14/D14-1 -> 0.2208 | F15: =F14/E14-1 -> 0.2 | G15: =G14/F14-1 -> 0.19 | H15: =H14/G14-1 -> 0.17 | I15: =I14/H14-1 -> 0.16 | J15: =J14/I14-1 -> 0.12

Sheet Margin Cost Build
A1: Margin / Cost Build
A5: Fiscal year | B5: N/A | C5: N/A | D5: 2025A | E5: 2026E | F5: 2027E | G5: 2028E | H5: 2029E | I5: 2030E | J5: 2031E
A7: Operating profitability
A8: Revenue | B8: ='Historical Financials'!B$6 -> 0 | C8: ='Historical Financials'!C$6 -> 0 | D8: ='Historical Financials'!D$6 -> 13278 | E8: ='Revenue Build'!E$14 -> 16209.782 | F8: ='Revenue Build'!F$14 -> 19451.739 | G8: ='Revenue Build'!G$14 -> 23147.569 | H8: ='Revenue Build'!H$14 -> 27082.656 | I8: ='Revenue Build'!I$14 -> 31415.881 | J8: ='Revenue Build'!J$14 -> 35185.787
A9: Gross profit (not modeled) | B9: ='Historical Financials'!B$8 -> 0 | C9: ='Historical Financials'!C$8 -> 0 | D9: ='Historical Financials'!D$8 -> 10294.433
A10: Gross margin (not modeled) | B10: =IFERROR(B9/B8,"") | C10: =IFERROR(C9/C8,"") | D10: =D9/D8 -> 0.7753
A11: EBITDA margin assumption | B11: ='Historical Financials'!B$11 | C11: ='Historical Financials'!C$11 | D11: ='Historical Financials'!D$11 -> 0.22081639 | E11: =INDEX('Control Panel'!B$26:B$28,MATCH('Control Panel'!$B$10,'Control Panel'!$A$26:$A$28,0)) -> 0.215 | F11: =INDEX('Control Panel'!C$26:C$28,MATCH('Control Panel'!$B$10,'Control Panel'!$A$26:$A$28,0)) -> 0.23 | G11: =INDEX('Control Panel'!D$26:D$28,MATCH('Control Panel'!$B$10,'Control Panel'!$A$26:$A$28,0)) -> 0.25 | H11: =INDEX('Control Panel'!E$26:E$28,MATCH('Control Panel'!$B$10,'Control Panel'!$A$26:$A$28,0)) -> 0.27 | I11: =INDEX('Control Panel'!F$26:F$28,MATCH('Control Panel'!$B$10,'Control Panel'!$A$26:$A$28,0)) -> 0.29 | J11: =INDEX('Control Panel'!G$26:G$28,MATCH('Control Panel'!$B$10,'Control Panel'!$A$26:$A$28,0)) -> 0.31
A12: EBITDA | B12: ='Historical Financials'!B$10 -> 0 | C12: ='Historical Financials'!C$10 -> 0 | D12: ='Historical Financials'!D$10 -> 2932 | E12: =E8*E11 -> 3485.1032 | F12: =F8*F11 -> 4473.8999 | G12: =G8*G11 -> 5786.8923 | H12: =H8*H11 -> 7312.3171 | I12: =I8*I11 -> 9110.6055 | J12: =J8*J11 -> 10907.594
A13: D&A | B13: ='Historical Financials'!B$12 -> 0 | C13: ='Historical Financials'!C$12 -> 0 | D13: ='Historical Financials'!D$12 -> 738 | E13: ='Capex D&A'!E$12 -> 810.48912 | F13: ='Capex D&A'!F$12 -> 972.58694 | G13: ='Capex D&A'!G$12 -> 1157.3785 | H13: ='Capex D&A'!H$12 -> 1354.1328 | I13: ='Capex D&A'!I$12 -> 1570.7941 | J13: ='Capex D&A'!J$12 -> 1759.2893
A14: D&A % revenue | B14: =IFERROR(B13/B8,"") | C14: =IFERROR(C13/C8,"") | D14: =D13/D8 -> 0.05558066 | E14: =E13/E8 -> 0.05 | F14: =F13/F8 -> 0.05 | G14: =G13/G8 -> 0.05 | H14: =H13/H8 -> 0.05 | I14: =I13/I8 -> 0.05 | J14: =J13/J8 -> 0.05
A15: EBIT | B15: =B12-B13 -> 0 | C15: =C12-C13 -> 0 | D15: =D12-D13 -> 2194 | E15: =E12-E13 -> 2674.6141 | F15: =F12-F13 -> 3501.313 | G15: =G12-G13 -> 4629.5139 | H15: =H12-H13 -> 5958.1843 | I15: =I12-I13 -> 7539.8114 | J15: =J12-J13 -> 9148.3045
A16: EBIT margin | B16: =IFERROR(B15/B8,"") | C16: =IFERROR(C15/C8,"") | D16: =D15/D8 -> 0.16523573 | E16: =E15/E8 -> 0.165 | F16: =F15/F8 -> 0.18 | G16: =G15/G8 -> 0.2 | H16: =H15/H8 -> 0.22 | I16: =I15/I8 -> 0.24 | J16: =J15/J8 -> 0.26
A17: Margin expansion / compression vs prior year | B17: - | C17: =IF(AND(ISNUMBER(B16),ISNUMBER(C16)),C16-B16,"") | D17: =IF(AND(ISNUMBER(C16),ISNUMBER(D16)),D16-C16,"") | E17: =E16-D16 -> -0.00023572827 | F17: =F16-E16 -> 0.015 | G17: =G16-F16 -> 0.02 | H17: =H16-G16 -> 0.02 | I17: =I16-H16 -> 0.02 | J17: =J16-I16 -> 0.02
A18: Cash taxes | B18: ='Historical Financials'!B$15 -> 0 | C18: ='Historical Financials'!C$15 -> 0 | D18: ='Historical Financials'!D$15 -> 461 | E18: ='Tax Schedule'!E$12 -> 561.66896 | F18: ='Tax Schedule'!F$12 -> 735.27573 | G18: ='Tax Schedule'!G$12 -> 972.19791 | H18: ='Tax Schedule'!H$12 -> 1251.2187 | I18: ='Tax Schedule'!I$12 -> 1583.3604 | J18: ='Tax Schedule'!J$12 -> 1921.144

Sheet Working Capital
A1: Working Capital
A5: Fiscal year | B5: N/A | C5: N/A | D5: 2025A | E5: 2026E | F5: 2027E | G5: 2028E | H5: 2029E | I5: 2030E | J5: 2031E
A7: Operating working capital
A8: Revenue | B8: ='Historical Financials'!B$6 -> 0 | C8: ='Historical Financials'!C$6 -> 0 | D8: ='Historical Financials'!D$6 -> 13278 | E8: ='Revenue Build'!E$14 -> 16209.782 | F8: ='Revenue Build'!F$14 -> 19451.739 | G8: ='Revenue Build'!G$14 -> 23147.569 | H8: ='Revenue Build'!H$14 -> 27082.656 | I8: ='Revenue Build'!I$14 -> 31415.881 | J8: ='Revenue Build'!J$14 -> 35185.787
A9: AR % revenue | B9: ="" | C9: ="" | D9: ="" | E9: ='Control Panel'!B$61 -> -0.39 | F9: ='Control Panel'!C$61 -> -0.39 | G9: ='Control Panel'!D$61 -> -0.39 | H9: ='Control Panel'!E$61 -> -0.39 | I9: ='Control Panel'!F$61 -> -0.39 | J9: ='Control Panel'!G$61 -> -0.39
A10: Accounts receivable | B10: ="" | C10: ="" | D10: ="" | E10: =E8*E9 -> -6321.8151 | F10: =F8*F9 -> -7586.1782 | G10: =G8*G9 -> -9027.552 | H10: =H8*H9 -> -10562.236 | I10: =I8*I9 -> -12252.194 | J10: =J8*J9 -> -13722.457
A11: Inventory % revenue | B11: ="" | C11: ="" | D11: ="" | E11: ='Control Panel'!B$62 -> 0 | F11: ='Control Panel'!C$62 -> 0 | G11: ='Control Panel'!D$62 -> 0 | H11: ='Control Panel'!E$62 -> 0 | I11: ='Control Panel'!F$62 -> 0 | J11: ='Control Panel'!G$62 -> 0
A12: Inventory | B12: ="" | C12: ="" | D12: ="" | E12: =E8*E11 -> 0 | F12: =F8*F11 -> 0 | G12: =G8*G11 -> 0 | H12: =H8*H11 -> 0 | I12: =I8*I11 -> 0 | J12: =J8*J11 -> 0
A13: AP % revenue | B13: ="" | C13: ="" | D13: ="" | E13: ='Control Panel'!B$63 -> 0 | F13: ='Control Panel'!C$63 -> 0 | G13: ='Control Panel'!D$63 -> 0 | H13: ='Control Panel'!E$63 -> 0 | I13: ='Control Panel'!F$63 -> 0 | J13: ='Control Panel'!G$63 -> 0
A14: Accounts payable | B14: ="" | C14: ="" | D14: ="" | E14: =E8*E13 -> 0 | F14: =F8*F13 -> 0 | G14: =G8*G13 -> 0 | H14: =H8*H13 -> 0 | I14: =I8*I13 -> 0 | J14: =J8*J13 -> 0
A15: Other current assets / liabilities net | B15: ="" | C15: ="" | D15: ="" | E15: =E8*('Control Panel'!B$64-'Control Panel'!B$65) -> 0 | F15: =F8*('Control Panel'!C$64-'Control Panel'!C$65) -> 0 | G15: =G8*('Control Panel'!D$64-'Control Panel'!D$65) -> 0 | H15: =H8*('Control Panel'!E$64-'Control Panel'!E$65) -> 0 | I15: =I8*('Control Panel'!F$64-'Control Panel'!F$65) -> 0 | J15: =J8*('Control Panel'!G$64-'Control Panel'!G$65) -> 0
A16: Operating NWC | B16: ="" | C16: ="" | D16: ='Historical Financials'!D$18 -> -5150 | E16: =E10+E12-E14+E15 -> -6321.8151 | F16: =F10+F12-F14+F15 -> -7586.1782 | G16: =G10+G12-G14+G15 -> -9027.552 | H16: =H10+H12-H14+H15 -> -10562.236 | I16: =I10+I12-I14+I15 -> -12252.194 | J16: =J10+J12-J14+J15 -> -13722.457
A17: Change in NWC | B17: ="" | C17: ="" | D17: -1078 | E17: =E16-D16 -> -1171.8151 | F17: =F16-E16 -> -1264.363 | G17: =G16-F16 -> -1441.3739 | H17: =H16-G16 -> -1534.6838 | I17: =I16-H16 -> -1689.9577 | J17: =J16-I16 -> -1470.2632
A18: NWC % revenue | B18: ="" | C18: ="" | D18: =IFERROR(D16/D8,"") -> -0.38785962 | E18: =E16/E8 -> -0.39 | F18: =F16/F8 -> -0.39 | G18: =G16/G8 -> -0.39 | H18: =H16/H8 -> -0.39 | I18: =I16/I8 -> -0.39 | J18: =J16/J8 -> -0.39
A19: Cash flow impact of NWC | B19: ="" | C19: ="" | D19: =-D17 -> 1078 | E19: =-E17 -> 1171.8151 | F19: =-F17 -> 1264.363 | G19: =-G17 -> 1441.3739 | H19: =-H17 -> 1534.6838 | I19: =-I17 -> 1689.9577 | J19: =-J17 -> 1470.2632

Sheet Capex D&A
A1: Capex and D&A
A5: Fiscal year | B5: N/A | C5: N/A | D5: 2025A | E5: 2026E | F5: 2027E | G5: 2028E | H5: 2029E | I5: 2030E | J5: 2031E
A7: Capital expenditure and depreciation schedule
A8: Revenue | B8: ='Historical Financials'!B$6 -> 0 | C8: ='Historical Financials'!C$6 -> 0 | D8: ='Historical Financials'!D$6 -> 13278 | E8: ='Revenue Build'!E$14 -> 16209.782 | F8: ='Revenue Build'!F$14 -> 19451.739 | G8: ='Revenue Build'!G$14 -> 23147.569 | H8: ='Revenue Build'!H$14 -> 27082.656 | I8: ='Revenue Build'!I$14 -> 31415.881 | J8: ='Revenue Build'!J$14 -> 35185.787
A9: Capex | B9: ='Historical Financials'!B$17 -> 0 | C9: ='Historical Financials'!C$17 -> 0 | D9: ='Historical Financials'!D$17 -> 868 | E9: =E8*E10 -> 972.58694 | F9: =F8*F10 -> 1167.1043 | G9: =G8*G10 -> 1388.8542 | H9: =H8*H10 -> 1624.9594 | I9: =I8*I10 -> 1884.9529 | J9: =J8*J10 -> 2111.1472
A10: Capex % revenue | B10: =IFERROR(B9/B8,"") | C10: =IFERROR(C9/C8,"") | D10: =D9/D8 -> 0.065371291 | E10: =INDEX('Control Panel'!B$41:B$43,MATCH('Control Panel'!$B$10,'Control Panel'!$A$41:$A$43,0)) -> 0.06 | F10: =INDEX('Control Panel'!C$41:C$43,MATCH('Control Panel'!$B$10,'Control Panel'!$A$41:$A$43,0)) -> 0.06 | G10: =INDEX('Control Panel'!D$41:D$43,MATCH('Control Panel'!$B$10,'Control Panel'!$A$41:$A$43,0)) -> 0.06 | H10: =INDEX('Control Panel'!E$41:E$43,MATCH('Control Panel'!$B$10,'Control Panel'!$A$41:$A$43,0)) -> 0.06 | I10: =INDEX('Control Panel'!F$41:F$43,MATCH('Control Panel'!$B$10,'Control Panel'!$A$41:$A$43,0)) -> 0.06 | J10: =INDEX('Control Panel'!G$41:G$43,MATCH('Control Panel'!$B$10,'Control Panel'!$A$41:$A$43,0)) -> 0.06
A11: Beginning PP&E | B11: n.m. | C11: n.m. | E11: =D13 -> 2289 | F11: =E13 -> 2451.0978 | G11: =F13 -> 2645.6152 | H11: =G13 -> 2877.0909 | I11: =H13 -> 3147.9175 | J11: =I13 -> 3462.0763
A12: D&A | B12: ='Historical Financials'!B$12 -> 0 | C12: ='Historical Financials'!C$12 -> 0 | D12: ='Historical Financials'!D$12 -> 738 | E12: =E8*E14 -> 810.48912 | F12: =F8*F14 -> 972.58694 | G12: =G8*G14 -> 1157.3785 | H12: =H8*H14 -> 1354.1328 | I12: =I8*I14 -> 1570.7941 | J12: =J8*J14 -> 1759.2893
A13: Ending PP&E | B13: n.m. | C13: n.m. | D13: 2289 | E13: =E11+E9-E12 -> 2451.0978 | F13: =F11+F9-F12 -> 2645.6152 | G13: =G11+G9-G12 -> 2877.0909 | H13: =H11+H9-H12 -> 3147.9175 | I13: =I11+I9-I12 -> 3462.0763 | J13: =J11+J9-J12 -> 3813.9341
A14: D&A % revenue | B14: =IFERROR(B12/B8,"") | C14: =IFERROR(C12/C8,"") | D14: =D12/D8 -> 0.05558066 | E14: =INDEX('Control Panel'!B$36:B$38,MATCH('Control Panel'!$B$10,'Control Panel'!$A$36:$A$38,0)) -> 0.05 | F14: =INDEX('Control Panel'!C$36:C$38,MATCH('Control Panel'!$B$10,'Control Panel'!$A$36:$A$38,0)) -> 0.05 | G14: =INDEX('Control Panel'!D$36:D$38,MATCH('Control Panel'!$B$10,'Control Panel'!$A$36:$A$38,0)) -> 0.05 | H14: =INDEX('Control Panel'!E$36:E$38,MATCH('Control Panel'!$B$10,'Control Panel'!$A$36:$A$38,0)) -> 0.05 | I14: =INDEX('Control Panel'!F$36:F$38,MATCH('Control Panel'!$B$10,'Control Panel'!$A$36:$A$38,0)) -> 0.05 | J14: =INDEX('Control Panel'!G$36:G$38,MATCH('Control Panel'!$B$10,'Control Panel'!$A$36:$A$38,0)) -> 0.05
A15: D&A % beginning PP&E | B15: n.m. | C15: n.m. | E15: =E12/E11 -> 0.35408 | F15: =F12/F11 -> 0.39679646 | G15: =G12/G11 -> 0.43747044 | H15: =H12/H11 -> 0.47066042 | I15: =I12/I11 -> 0.49899467 | J15: =J12/J11 -> 0.50816019

Sheet Tax Schedule
A1: Tax Schedule
A5: Fiscal year | B5: N/A | C5: N/A | D5: 2025A | E5: 2026E | F5: 2027E | G5: 2028E | H5: 2029E | I5: 2030E | J5: 2031E
A7: Book and cash tax calculation
A8: EBIT | B8: ='Historical Financials'!B$13 -> 0 | C8: ='Historical Financials'!C$13 -> 0 | D8: ='Historical Financials'!D$13 -> 2194 | E8: ='Margin Cost Build'!E$15 -> 2674.6141 | F8: ='Margin Cost Build'!F$15 -> 3501.313 | G8: ='Margin Cost Build'!G$15 -> 4629.5139 | H8: ='Margin Cost Build'!H$15 -> 5958.1843 | I8: ='Margin Cost Build'!I$15 -> 7539.8114 | J8: ='Margin Cost Build'!J$15 -> 9148.3045
A9: Statutory tax rate | B9: =IFERROR('Historical Financials'!B$15/B8,"") | C9: =IFERROR('Historical Financials'!C$15/C8,"") | D9: ='Historical Financials'!D$15/D8 -> 0.21011851 | E9: =INDEX('Control Panel'!B$51:B$53,MATCH('Control Panel'!$B$10,'Control Panel'!$A$51:$A$53,0)) -> 0.21 | F9: =INDEX('Control Panel'!C$51:C$53,MATCH('Control Panel'!$B$10,'Control Panel'!$A$51:$A$53,0)) -> 0.21 | G9: =INDEX('Control Panel'!D$51:D$53,MATCH('Control Panel'!$B$10,'Control Panel'!$A$51:$A$53,0)) -> 0.21 | H9: =INDEX('Control Panel'!E$51:E$53,MATCH('Control Panel'!$B$10,'Control Panel'!$A$51:$A$53,0)) -> 0.21 | I9: =INDEX('Control Panel'!F$51:F$53,MATCH('Control Panel'!$B$10,'Control Panel'!$A$51:$A$53,0)) -> 0.21 | J9: =INDEX('Control Panel'!G$51:G$53,MATCH('Control Panel'!$B$10,'Control Panel'!$A$51:$A$53,0)) -> 0.21
A10: Cash tax rate | B10: =B9 | C10: =C9 | D10: =D9 -> 0.21011851 | E10: =INDEX('Control Panel'!B$56:B$58,MATCH('Control Panel'!$B$10,'Control Panel'!$A$56:$A$58,0)) -> 0.21 | F10: =INDEX('Control Panel'!C$56:C$58,MATCH('Control Panel'!$B$10,'Control Panel'!$A$56:$A$58,0)) -> 0.21 | G10: =INDEX('Control Panel'!D$56:D$58,MATCH('Control Panel'!$B$10,'Control Panel'!$A$56:$A$58,0)) -> 0.21 | H10: =INDEX('Control Panel'!E$56:E$58,MATCH('Control Panel'!$B$10,'Control Panel'!$A$56:$A$58,0)) -> 0.21 | I10: =INDEX('Control Panel'!F$56:F$58,MATCH('Control Panel'!$B$10,'Control Panel'!$A$56:$A$58,0)) -> 0.21 | J10: =INDEX('Control Panel'!G$56:G$58,MATCH('Control Panel'!$B$10,'Control Panel'!$A$56:$A$58,0)) -> 0.21
A11: NOL usage placeholder | B11: 0 | C11: 0 | D11: 0 | E11: 0 | F11: 0 | G11: 0 | H11: 0 | I11: 0 | J11: 0
A12: Cash taxes | B12: ='Historical Financials'!B$15 -> 0 | C12: ='Historical Financials'!C$15 -> 0 | D12: ='Historical Financials'!D$15 -> 461 | E12: =MAX(0,E8*E10-E11) -> 561.66896 | F12: =MAX(0,F8*F10-F11) -> 735.27573 | G12: =MAX(0,G8*G10-G11) -> 972.19791 | H12: =MAX(0,H8*H10-H11) -> 1251.2187 | I12: =MAX(0,I8*I10-I11) -> 1583.3604 | J12: =MAX(0,J8*J10-J11) -> 1921.144
A13: Deferred tax placeholder | B13: 0 | C13: 0 | D13: 0 | E13: =E8*E9-E12 -> 0 | F13: =F8*F9-F12 -> 0 | G13: =G8*G9-G12 -> 0 | H13: =H8*H9-H12 -> 0 | I13: =I8*I9-I12 -> 0 | J13: =J8*J9-J12 -> 0
A14: Tax warning / simplified treatment | B14: Replace placeholder NOL/deferred tax logic where material | C14: Replace placeholder NOL/deferred tax logic where material | D14: Replace placeholder NOL/deferred tax logic where material | E14: Simplified cash tax schedule; add NOL detail if material | F14: Simplified cash tax schedule; add NOL detail if material | G14: Simplified cash tax schedule; add NOL detail if material | H14: Simplified cash tax schedule; add NOL detail if material | I14: Simplified cash tax schedule; add NOL detail if material | J14: Simplified cash tax schedule; add NOL detail if material

Sheet Unlevered FCF
A1: Unlevered Free Cash Flow
A5: Fiscal year | B5: N/A | C5: N/A | D5: 2025A | E5: 2026E | F5: 2027E | G5: 2028E | H5: 2029E | I5: 2030E | J5: 2031E
A7: Core DCF cash flows
A8: EBIT | B8: ='Historical Financials'!B$13 -> 0 | C8: ='Historical Financials'!C$13 -> 0 | D8: ='Historical Financials'!D$13 -> 2194 | E8: ='Margin Cost Build'!E$15 -> 2674.6141 | F8: ='Margin Cost Build'!F$15 -> 3501.313 | G8: ='Margin Cost Build'!G$15 -> 4629.5139 | H8: ='Margin Cost Build'!H$15 -> 5958.1843 | I8: ='Margin Cost Build'!I$15 -> 7539.8114 | J8: ='Margin Cost Build'!J$15 -> 9148.3045
A9: Less: cash taxes | B9: ='Historical Financials'!B$15 -> 0 | C9: ='Historical Financials'!C$15 -> 0 | D9: ='Historical Financials'!D$15 -> 461 | E9: ='Tax Schedule'!E$12 -> 561.66896 | F9: ='Tax Schedule'!F$12 -> 735.27573 | G9: ='Tax Schedule'!G$12 -> 972.19791 | H9: ='Tax Schedule'!H$12 -> 1251.2187 | I9: ='Tax Schedule'!I$12 -> 1583.3604 | J9: ='Tax Schedule'!J$12 -> 1921.144
A10: NOPAT | B10: =B8-B9 -> 0 | C10: =C8-C9 -> 0 | D10: =D8-D9 -> 1733 | E10: =E8-E9 -> 2112.9451 | F10: =F8-F9 -> 2766.0373 | G10: =G8-G9 -> 3657.3159 | H10: =H8-H9 -> 4706.9656 | I10: =I8-I9 -> 5956.451 | J10: =J8-J9 -> 7227.1606
A11: Plus: D&A | B11: ='Historical Financials'!B$12 -> 0 | C11: ='Historical Financials'!C$12 -> 0 | D11: ='Historical Financials'!D$12 -> 738 | E11: ='Capex D&A'!E$12 -> 810.48912 | F11: ='Capex D&A'!F$12 -> 972.58694 | G11: ='Capex D&A'!G$12 -> 1157.3785 | H11: ='Capex D&A'!H$12 -> 1354.1328 | I11: ='Capex D&A'!I$12 -> 1570.7941 | J11: ='Capex D&A'!J$12 -> 1759.2893
A12: Less: Capex | B12: ='Historical Financials'!B$17 -> 0 | C12: ='Historical Financials'!C$17 -> 0 | D12: ='Historical Financials'!D$17 -> 868 | E12: ='Capex D&A'!E$9 -> 972.58694 | F12: ='Capex D&A'!F$9 -> 1167.1043 | G12: ='Capex D&A'!G$9 -> 1388.8542 | H12: ='Capex D&A'!H$9 -> 1624.9594 | I12: ='Capex D&A'!I$9 -> 1884.9529 | J12: ='Capex D&A'!J$9 -> 2111.1472
A13: Less: Change in NWC | D13: -1078 | E13: ='Working Capital'!E$17 -> -1171.8151 | F13: ='Working Capital'!F$17 -> -1264.363 | G13: ='Working Capital'!G$17 -> -1441.3739 | H13: ='Working Capital'!H$17 -> -1534.6838 | I13: ='Working Capital'!I$17 -> -1689.9577 | J13: ='Working Capital'!J$17 -> -1470.2632
A14: Unlevered free cash flow | B14: =B10+B11-B12-B13 -> 0 | C14: =C10+C11-C12-C13 -> 0 | D14: =D10+D11-D12-D13 -> 2681 | E14: =E10+E11-E12-E13 -> 3122.6624 | F14: =F10+F11-F12-F13 -> 3835.8829 | G14: =G10+G11-G12-G13 -> 4867.2141 | H14: =H10+H11-H12-H13 -> 5970.8229 | I14: =I10+I11-I12-I13 -> 7332.25 | J14: =J10+J11-J12-J13 -> 8345.566
A15: Discount period | B15: n/a | C15: n/a | D15: n/a | E15: =IF('Control Panel'!$B$11="Yes",1-0.5,1) -> 1 | F15: =IF('Control Panel'!$B$11="Yes",2-0.5,2) -> 2 | G15: =IF('Control Panel'!$B$11="Yes",3-0.5,3) -> 3 | H15: =IF('Control Panel'!$B$11="Yes",4-0.5,4) -> 4 | I15: =IF('Control Panel'!$B$11="Yes",5-0.5,5) -> 5 | J15: =IF('Control Panel'!$B$11="Yes",6-0.5,6) -> 6
A16: Discount factor | B16: n/a | C16: n/a | D16: n/a | E16: =1/(1+'Control Panel'!$B$78)^E15 -> 0.92057593 | F16: =1/(1+'Control Panel'!$B$78)^F15 -> 0.84746004 | G16: =1/(1+'Control Panel'!$B$78)^G15 -> 0.78015132 | H16: =1/(1+'Control Panel'!$B$78)^H15 -> 0.71818853 | I16: =1/(1+'Control Panel'!$B$78)^I15 -> 0.66114707 | J16: =1/(1+'Control Panel'!$B$78)^J15 -> 0.60863608
A17: Present value of FCF | B17: n/a | C17: n/a | D17: n/a | E17: =E14*E16 -> 2874.6479 | F17: =F14*F16 -> 3250.7575 | G17: =G14*G16 -> 3797.1635 | H17: =H14*H16 -> 4288.1765 | I17: =I14*I16 -> 4847.6956 | J17: =J14*J16 -> 5079.4126

Sheet WACC
A1: Weighted Average Cost of Capital
A3: Cost of equity
A4: Risk-free rate | B4: ='Control Panel'!$B$69 -> 0.0463 | C4: Source / calculation basis | D4: placeholder
A5: Beta | B5: ='Control Panel'!$B$70 -> 0.96 | C5: Source / calculation basis | D5: placeholder
A6: Market risk premium | B6: ='Control Panel'!$B$71 -> 0.045 | C6: Source / calculation basis | D6: placeholder
A7: Size premium | B7: ='Control Panel'!$B$72 -> 0 | C7: Source / calculation basis | D7: placeholder
A8: Cost of equity | B8: =B4+B5*B6+B7 -> 0.0895 | C8: Source / calculation basis | D8: derived
A10: Cost of debt and capital structure
A11: Pre-tax cost of debt | B11: ='Control Panel'!$B$73 -> 0.055 | C11: Source / calculation basis | D11: placeholder
A12: Tax rate | B12: ='Tax Schedule'!J$9 -> 0.21 | C12: Source / calculation basis | D12: placeholder
A13: After-tax cost of debt | B13: =B11*(1-B12) -> 0.04345 | C13: Source / calculation basis | D13: derived
A14: Target debt / capital | B14: ='Control Panel'!$B$74 -> 0.07 | C14: Source / calculation basis | D14: placeholder
A15: Target equity / capital | B15: ='Control Panel'!$B$75 -> 0.93 | C15: Source / calculation basis | D15: placeholder
A16: WACC formula check | B16: =B14+B15 -> 1 | C16: Source / calculation basis | D16: derived
A17: Calculated WACC | B17: =B8*B15+B13*B14 -> 0.0862765 | C17: Source / calculation basis | D17: derived
A19: Source notes
A20: Risk-free source | B20: ='Source Notes'!B7 -> 10-year Treasury, observed beta, and analyst ERP/company-risk assumptions
A21: Market data confidence | B21: ='Source Notes'!E7 -> Medium
A22: WACC caveat | B22: Replace illustrative assumptions with market data as of valuation date

Sheet Terminal Value
A1: Terminal Value
A3: Terminal value calculation
A4: Selected method | B4: ='Control Panel'!$B$14 -> Gordon Growth
A5: Selected WACC | B5: ='Control Panel'!$B$78 -> 0.0862765
A6: Terminal growth rate | B6: ='Control Panel'!$B$83 -> 0.03
A7: Exit multiple | B7: ='Control Panel'!$B$84 -> 15
A8: Terminal EBITDA | B8: ='Margin Cost Build'!J$12 -> 10907.594
A9: Terminal FCF | B9: ='Unlevered FCF'!J$14 -> 8345.566
A10: Gordon growth terminal value | B10: =B9*(1+B6)/(B5-B6) -> 152744.63
A11: Exit multiple terminal value | B11: =B8*B7 -> 163613.91
A12: Selected terminal value | B12: =IF(B4="Gordon Growth",B10,B11) -> 152744.63
A13: Terminal discount factor | B13: =1/(1+B5)^6 -> 0.60863608
A14: PV of terminal value | B14: =B12*B13 -> 92965.89
A15: Implied terminal EBITDA multiple | B15: =B12/B8 -> 14.003512
A16: Implied terminal FCF yield | B16: =B9/B12 -> 0.054637379
A17: Implied perpetual growth cross-check | B17: =B5-B9/B12 -> 0.031639121
A20: Terminal value sanity checks
A21: Terminal value / enterprise value | B21: =B14/'DCF Valuation'!B$8 -> 0.79387633
A22: Growth below WACC | B22: =IF(B6<B5,"OK","FAIL") -> OK
A23: Positive selected terminal value | B23: =IF(B12>0,"OK","FAIL") -> OK

Sheet DCF Valuation
A1: DCF Valuation
A3: Enterprise value
A4: PV of forecast FCF | B4: =SUM('Unlevered FCF'!E$17:J$17) -> 24137.854
A5: PV of terminal value | B5: ='Terminal Value'!B$14 -> 92965.89
A6: Enterprise value | B6: =B4+B5 -> 117103.74
A7: Terminal value % of enterprise value | B7: =B5/B6 -> 0.79387633
A8: Enterprise value check | B8: =B4+B5 -> 117103.74
A10: EV-to-equity bridge
A11: Less: net debt | B11: ='Control Panel'!$B$85 -> 810
A12: Less: minority interest | B12: ='Control Panel'!$B$87 -> 0
A13: Less: preferred stock | B13: ='Control Panel'!$B$88 -> 0
A14: Plus: non-operating assets | B14: ='Control Panel'!$B$89 -> 0
A15: Other equity adjustments | B15: ='Control Panel'!$B$90 -> 0
A16: Equity value | B16: =B6-B11-B12-B13+B14+B15 -> 116293.74
A17: Diluted shares | B17: ='Control Panel'!$B$86 -> 1034
A18: Implied share price | B18: =B16/B17 -> 112.46977
A19: Current share price | B19: ='Control Panel'!$B$12 -> 97.35
A20: Upside / downside | B20: =B18/B19-1 -> 0.15531353
A21: Implied EV / EBITDA | B21: =B6/'Margin Cost Build'!J$12 -> 10.735983
A22: Implied FCF yield | B22: ='Unlevered FCF'!J$14/B6 -> 0.071266432

Sheet Sensitivities
A1: Sensitivities
A3: Implied share price by WACC and terminal growth
A4: Terminal growth | B4: 0.075 | C4: 0.08 | D4: 0.085 | E4: 0.09 | F4: 0.095 | G4: 0.1 | H4: 0.105
A5: 0.015 | B5: =(('Unlevered FCF'!E$14/(1+B$4)^1+'Unlevered FCF'!F$14/(1+B$4)^2+'Unlevered FCF'!G$14/(1+B$4)^3+'Unlevered FCF'!H$14/(1+B$4)^4+'Unlevered FCF'!I$14/(1+B$4)^5+'Unlevered FCF'!J$14/(1+B$4)^6)+('Unlevered FCF'!J$14*(1+$A5)/(B$4-$A5))/(1+B$4)^6-'Control Panel'!$B$85-'Control Panel'!$B$87-'Control Panel'!$B$88+'Control Panel'!$B$89+'Control Panel'!$B$90)/'Control Panel'!$B$86 -> 111.98897 | C5: =(('Unlevered FCF'!E$14/(1+C$4)^1+'Unlevered FCF'!F$14/(1+C$4)^2+'Unlevered FCF'!G$14/(1+C$4)^3+'Unlevered FCF'!H$14/(1+C$4)^4+'Unlevered FCF'!I$14/(1+C$4)^5+'Unlevered FCF'!J$14/(1+C$4)^6)+('Unlevered FCF'!J$14*(1+$A5)/(C$4-$A5))/(1+C$4)^6-'Control Panel'!$B$85-'Control Panel'!$B$87-'Control Panel'!$B$88+'Control Panel'!$B$89+'Control Panel'!$B$90)/'Control Panel'!$B$86 -> 102.5097 | D5: =(('Unlevered FCF'!E$14/(1+D$4)^1+'Unlevered FCF'!F$14/(1+D$4)^2+'Unlevered FCF'!G$14/(1+D$4)^3+'Unlevered FCF'!H$14/(1+D$4)^4+'Unlevered FCF'!I$14/(1+D$4)^5+'Unlevered FCF'!J$14/(1+D$4)^6)+('Unlevered FCF'!J$14*(1+$A5)/(D$4-$A5))/(1+D$4)^6-'Control Panel'!$B$85-'Control Panel'!$B$87-'Control Panel'!$B$88+'Control Panel'!$B$89+'Control Panel'!$B$90)/'Control Panel'!$B$86 -> 94.400373 | E5: =(('Unlevered FCF'!E$14/(1+E$4)^1+'Unlevered FCF'!F$14/(1+E$4)^2+'Unlevered FCF'!G$14/(1+E$4)^3+'Unlevered FCF'!H$14/(1+E$4)^4+'Unlevered FCF'!I$14/(1+E$4)^5+'Unlevered FCF'!J$14/(1+E$4)^6)+('Unlevered FCF'!J$14*(1+$A5)/(E$4-$A5))/(1+E$4)^6-'Control Panel'!$B$85-'Control Panel'!$B$87-'Control Panel'!$B$88+'Control Panel'!$B$89+'Control Panel'!$B$90)/'Control Panel'!$B$86 -> 87.386596 | F5: =(('Unlevered FCF'!E$14/(1+F$4)^1+'Unlevered FCF'!F$14/(1+F$4)^2+'Unlevered FCF'!G$14/(1+F$4)^3+'Unlevered FCF'!H$14/(1+F$4)^4+'Unlevered FCF'!I$14/(1+F$4)^5+'Unlevered FCF'!J$14/(1+F$4)^6)+('Unlevered FCF'!J$14*(1+$A5)/(F$4-$A5))/(1+F$4)^6-'Control Panel'!$B$85-'Control Panel'!$B$87-'Control Panel'!$B$88+'Control Panel'!$B$89+'Control Panel'!$B$90)/'Control Panel'!$B$86 -> 81.262598 | G5: =(('Unlevered FCF'!E$14/(1+G$4)^1+'Unlevered FCF'!F$14/(1+G$4)^2+'Unlevered FCF'!G$14/(1+G$4)^3+'Unlevered FCF'!H$14/(1+G$4)^4+'Unlevered FCF'!I$14/(1+G$4)^5+'Unlevered FCF'!J$14/(1+G$4)^6)+('Unlevered FCF'!J$14*(1+$A5)/(G$4-$A5))/(1+G$4)^6-'Control Panel'!$B$85-'Control Panel'!$B$87-'Control Panel'!$B$88+'Control Panel'!$B$89+'Control Panel'!$B$90)/'Control Panel'!$B$86 -> 75.871031 | H5: =(('Unlevered FCF'!E$14/(1+H$4)^1+'Unlevered FCF'!F$14/(1+H$4)^2+'Unlevered FCF'!G$14/(1+H$4)^3+'Unlevered FCF'!H$14/(1+H$4)^4+'Unlevered FCF'!I$14/(1+H$4)^5+'Unlevered FCF'!J$14/(1+H$4)^6)+('Unlevered FCF'!J$14*(1+$A5)/(H$4-$A5))/(1+H$4)^6-'Control Panel'!$B$85-'Control Panel'!$B$87-'Control Panel'!$B$88+'Control Panel'!$B$89+'Control Panel'!$B$90)/'Control Panel'!$B$86 -> 71.089526
A6: 0.02 | B6: =(('Unlevered FCF'!E$14/(1+B$4)^1+'Unlevered FCF'!F$14/(1+B$4)^2+'Unlevered FCF'!G$14/(1+B$4)^3+'Unlevered FCF'!H$14/(1+B$4)^4+'Unlevered FCF'!I$14/(1+B$4)^5+'Unlevered FCF'!J$14/(1+B$4)^6)+('Unlevered FCF'!J$14*(1+$A6)/(B$4-$A6))/(1+B$4)^6-'Control Panel'!$B$85-'Control Panel'!$B$87-'Control Panel'!$B$88+'Control Panel'!$B$89+'Control Panel'!$B$90)/'Control Panel'!$B$86 -> 120.50719 | C6: =(('Unlevered FCF'!E$14/(1+C$4)^1+'Unlevered FCF'!F$14/(1+C$4)^2+'Unlevered FCF'!G$14/(1+C$4)^3+'Unlevered FCF'!H$14/(1+C$4)^4+'Unlevered FCF'!I$14/(1+C$4)^5+'Unlevered FCF'!J$14/(1+C$4)^6)+('Unlevered FCF'!J$14*(1+$A6)/(C$4-$A6))/(1+C$4)^6-'Control Panel'!$B$85-'Control Panel'!$B$87-'Control Panel'!$B$88+'Control Panel'!$B$89+'Control Panel'!$B$90)/'Control Panel'!$B$86 -> 109.55212 | D6: =(('Unlevered FCF'!E$14/(1+D$4)^1+'Unlevered FCF'!F$14/(1+D$4)^2+'Unlevered FCF'!G$14/(1+D$4)^3+'Unlevered FCF'!H$14/(1+D$4)^4+'Unlevered FCF'!I$14/(1+D$4)^5+'Unlevered FCF'!J$14/(1+D$4)^6)+('Unlevered FCF'!J$14*(1+$A6)/(D$4-$A6))/(1+D$4)^6-'Control Panel'!$B$85-'Control Panel'!$B$87-'Control Panel'!$B$88+'Control Panel'!$B$89+'Control Panel'!$B$90)/'Control Panel'!$B$86 -> 100.29892 | E6: =(('Unlevered FCF'!E$14/(1+E$4)^1+'Unlevered FCF'!F$14/(1+E$4)^2+'Unlevered FCF'!G$14/(1+E$4)^3+'Unlevered FCF'!H$14/(1+E$4)^4+'Unlevered FCF'!I$14/(1+E$4)^5+'Unlevered FCF'!J$14/(1+E$4)^6)+('Unlevered FCF'!J$14*(1+$A6)/(E$4-$A6))/(1+E$4)^6-'Control Panel'!$B$85-'Control Panel'!$B$87-'Control Panel'!$B$88+'Control Panel'!$B$89+'Control Panel'!$B$90)/'Control Panel'!$B$86 -> 92.382493 | F6: =(('Unlevered FCF'!E$14/(1+F$4)^1+'Unlevered FCF'!F$14/(1+F$4)^2+'Unlevered FCF'!G$14/(1+F$4)^3+'Unlevered FCF'!H$14/(1+F$4)^4+'Unlevered FCF'!I$14/(1+F$4)^5+'Unlevered FCF'!J$14/(1+F$4)^6)+('Unlevered FCF'!J$14*(1+$A6)/(F$4-$A6))/(1+F$4)^6-'Control Panel'!$B$85-'Control Panel'!$B$87-'Control Panel'!$B$88+'Control Panel'!$B$89+'Control Panel'!$B$90)/'Control Panel'!$B$86 -> 85.535111 | G6: =(('Unlevered FCF'!E$14/(1+G$4)^1+'Unlevered FCF'!F$14/(1+G$4)^2+'Unlevered FCF'!G$14/(1+G$4)^3+'Unlevered FCF'!H$14/(1+G$4)^4+'Unlevered FCF'!I$14/(1+G$4)^5+'Unlevered FCF'!J$14/(1+G$4)^6)+('Unlevered FCF'!J$14*(1+$A6)/(G$4-$A6))/(1+G$4)^6-'Control Panel'!$B$85-'Control Panel'!$B$87-'Control Panel'!$B$88+'Control Panel'!$B$89+'Control Panel'!$B$90)/'Control Panel'!$B$86 -> 79.555992 | H6: =(('Unlevered FCF'!E$14/(1+H$4)^1+'Unlevered FCF'!F$14/(1+H$4)^2+'Unlevered FCF'!G$14/(1+H$4)^3+'Unlevered FCF'!H$14/(1+H$4)^4+'Unlevered FCF'!I$14/(1+H$4)^5+'Unlevered FCF'!J$14/(1+H$4)^6)+('Unlevered FCF'!J$14*(1+$A6)/(H$4-$A6))/(1+H$4)^6-'Control Panel'!$B$85-'Control Panel'!$B$87-'Control Panel'!$B$88+'Control Panel'!$B$89+'Control Panel'!$B$90)/'Control Panel'!$B$86 -> 74.291608
A7: 0.025 | B7: =(('Unlevered FCF'!E$14/(1+B$4)^1+'Unlevered FCF'!F$14/(1+B$4)^2+'Unlevered FCF'!G$14/(1+B$4)^3+'Unlevered FCF'!H$14/(1+B$4)^4+'Unlevered FCF'!I$14/(1+B$4)^5+'Unlevered FCF'!J$14/(1+B$4)^6)+('Unlevered FCF'!J$14*(1+$A7)/(B$4-$A7))/(1+B$4)^6-'Control Panel'!$B$85-'Control Panel'!$B$87-'Control Panel'!$B$88+'Control Panel'!$B$89+'Control Panel'!$B$90)/'Control Panel'!$B$86 -> 130.72906 | C7: =(('Unlevered FCF'!E$14/(1+C$4)^1+'Unlevered FCF'!F$14/(1+C$4)^2+'Unlevered FCF'!G$14/(1+C$4)^3+'Unlevered FCF'!H$14/(1+C$4)^4+'Unlevered FCF'!I$14/(1+C$4)^5+'Unlevered FCF'!J$14/(1+C$4)^6)+('Unlevered FCF'!J$14*(1+$A7)/(C$4-$A7))/(1+C$4)^6-'Control Panel'!$B$85-'Control Panel'!$B$87-'Control Panel'!$B$88+'Control Panel'!$B$89+'Control Panel'!$B$90)/'Control Panel'!$B$86 -> 117.87498 | D7: =(('Unlevered FCF'!E$14/(1+D$4)^1+'Unlevered FCF'!F$14/(1+D$4)^2+'Unlevered FCF'!G$14/(1+D$4)^3+'Unlevered FCF'!H$14/(1+D$4)^4+'Unlevered FCF'!I$14/(1+D$4)^5+'Unlevered FCF'!J$14/(1+D$4)^6)+('Unlevered FCF'!J$14*(1+$A7)/(D$4-$A7))/(1+D$4)^6-'Control Panel'!$B$85-'Control Panel'!$B$87-'Control Panel'!$B$88+'Control Panel'!$B$89+'Control Panel'!$B$90)/'Control Panel'!$B$86 -> 107.18056 | E7: =(('Unlevered FCF'!E$14/(1+E$4)^1+'Unlevered FCF'!F$14/(1+E$4)^2+'Unlevered FCF'!G$14/(1+E$4)^3+'Unlevered FCF'!H$14/(1+E$4)^4+'Unlevered FCF'!I$14/(1+E$4)^5+'Unlevered FCF'!J$14/(1+E$4)^6)+('Unlevered FCF'!J$14*(1+$A7)/(E$4-$A7))/(1+E$4)^6-'Control Panel'!$B$85-'Control Panel'!$B$87-'Control Panel'!$B$88+'Control Panel'!$B$89+'Control Panel'!$B$90)/'Control Panel'!$B$86 -> 98.146989 | F7: =(('Unlevered FCF'!E$14/(1+F$4)^1+'Unlevered FCF'!F$14/(1+F$4)^2+'Unlevered FCF'!G$14/(1+F$4)^3+'Unlevered FCF'!H$14/(1+F$4)^4+'Unlevered FCF'!I$14/(1+F$4)^5+'Unlevered FCF'!J$14/(1+F$4)^6)+('Unlevered FCF'!J$14*(1+$A7)/(F$4-$A7))/(1+F$4)^6-'Control Panel'!$B$85-'Control Panel'!$B$87-'Control Panel'!$B$88+'Control Panel'!$B$89+'Control Panel'!$B$90)/'Control Panel'!$B$86 -> 90.417983 | G7: =(('Unlevered FCF'!E$14/(1+G$4)^1+'Unlevered FCF'!F$14/(1+G$4)^2+'Unlevered FCF'!G$14/(1+G$4)^3+'Unlevered FCF'!H$14/(1+G$4)^4+'Unlevered FCF'!I$14/(1+G$4)^5+'Unlevered FCF'!J$14/(1+G$4)^6)+('Unlevered FCF'!J$14*(1+$A7)/(G$4-$A7))/(1+G$4)^6-'Control Panel'!$B$85-'Control Panel'!$B$87-'Control Panel'!$B$88+'Control Panel'!$B$89+'Control Panel'!$B$90)/'Control Panel'!$B$86 -> 83.732282 | H7: =(('Unlevered FCF'!E$14/(1+H$4)^1+'Unlevered FCF'!F$14/(1+H$4)^2+'Unlevered FCF'!G$14/(1+H$4)^3+'Unlevered FCF'!H$14/(1+H$4)^4+'Unlevered FCF'!I$14/(1+H$4)^5+'Unlevered FCF'!J$14/(1+H$4)^6)+('Unlevered FCF'!J$14*(1+$A7)/(H$4-$A7))/(1+H$4)^6-'Control Panel'!$B$85-'Control Panel'!$B$87-'Control Panel'!$B$88+'Control Panel'!$B$89+'Control Panel'!$B$90)/'Control Panel'!$B$86 -> 77.89395
A8: 0.03 | B8: =(('Unlevered FCF'!E$14/(1+B$4)^1+'Unlevered FCF'!F$14/(1+B$4)^2+'Unlevered FCF'!G$14/(1+B$4)^3+'Unlevered FCF'!H$14/(1+B$4)^4+'Unlevered FCF'!I$14/(1+B$4)^5+'Unlevered FCF'!J$14/(1+B$4)^6)+('Unlevered FCF'!J$14*(1+$A8)/(B$4-$A8))/(1+B$4)^6-'Control Panel'!$B$85-'Control Panel'!$B$87-'Control Panel'!$B$88+'Control Panel'!$B$89+'Control Panel'!$B$90)/'Control Panel'!$B$86 -> 143.22246 | C8: =(('Unlevered FCF'!E$14/(1+C$4)^1+'Unlevered FCF'!F$14/(1+C$4)^2+'Unlevered FCF'!G$14/(1+C$4)^3+'Unlevered FCF'!H$14/(1+C$4)^4+'Unlevered FCF'!I$14/(1+C$4)^5+'Unlevered FCF'!J$14/(1+C$4)^6)+('Unlevered FCF'!J$14*(1+$A8)/(C$4-$A8))/(1+C$4)^6-'Control Panel'!$B$85-'Control Panel'!$B$87-'Control Panel'!$B$88+'Control Panel'!$B$89+'Control Panel'!$B$90)/'Control Panel'!$B$86 -> 127.86241 | D8: =(('Unlevered FCF'!E$14/(1+D$4)^1+'Unlevered FCF'!F$14/(1+D$4)^2+'Unlevered FCF'!G$14/(1+D$4)^3+'Unlevered FCF'!H$14/(1+D$4)^4+'Unlevered FCF'!I$14/(1+D$4)^5+'Unlevered FCF'!J$14/(1+D$4)^6)+('Unlevered FCF'!J$14*(1+$A8)/(D$4-$A8))/(1+D$4)^6-'Control Panel'!$B$85-'Control Panel'!$B$87-'Control Panel'!$B$88+'Control Panel'!$B$89+'Control Panel'!$B$90)/'Control Panel'!$B$86 -> 115.31341 | E8: =(('Unlevered FCF'!E$14/(1+E$4)^1+'Unlevered FCF'!F$14/(1+E$4)^2+'Unlevered FCF'!G$14/(1+E$4)^3+'Unlevered FCF'!H$14/(1+E$4)^4+'Unlevered FCF'!I$14/(1+E$4)^5+'Unlevered FCF'!J$14/(1+E$4)^6)+('Unlevered FCF'!J$14*(1+$A8)/(E$4-$A8))/(1+E$4)^6-'Control Panel'!$B$85-'Control Panel'!$B$87-'Control Panel'!$B$88+'Control Panel'!$B$89+'Control Panel'!$B$90)/'Control Panel'!$B$86 -> 104.87224 | F8: =(('Unlevered FCF'!E$14/(1+F$4)^1+'Unlevered FCF'!F$14/(1+F$4)^2+'Unlevered FCF'!G$14/(1+F$4)^3+'Unlevered FCF'!H$14/(1+F$4)^4+'Unlevered FCF'!I$14/(1+F$4)^5+'Unlevered FCF'!J$14/(1+F$4)^6)+('Unlevered FCF'!J$14*(1+$A8)/(F$4-$A8))/(1+F$4)^6-'Control Panel'!$B$85-'Control Panel'!$B$87-'Control Panel'!$B$88+'Control Panel'!$B$89+'Control Panel'!$B$90)/'Control Panel'!$B$86 -> 96.052066 | G8: =(('Unlevered FCF'!E$14/(1+G$4)^1+'Unlevered FCF'!F$14/(1+G$4)^2+'Unlevered FCF'!G$14/(1+G$4)^3+'Unlevered FCF'!H$14/(1+G$4)^4+'Unlevered FCF'!I$14/(1+G$4)^5+'Unlevered FCF'!J$14/(1+G$4)^6)+('Unlevered FCF'!J$14*(1+$A8)/(G$4-$A8))/(1+G$4)^6-'Control Panel'!$B$85-'Control Panel'!$B$87-'Control Panel'!$B$88+'Control Panel'!$B$89+'Control Panel'!$B$90)/'Control Panel'!$B$86 -> 88.505184 | H8: =(('Unlevered FCF'!E$14/(1+H$4)^1+'Unlevered FCF'!F$14/(1+H$4)^2+'Unlevered FCF'!G$14/(1+H$4)^3+'Unlevered FCF'!H$14/(1+H$4)^4+'Unlevered FCF'!I$14/(1+H$4)^5+'Unlevered FCF'!J$14/(1+H$4)^6)+('Unlevered FCF'!J$14*(1+$A8)/(H$4-$A8))/(1+H$4)^6-'Control Panel'!$B$85-'Control Panel'!$B$87-'Control Panel'!$B$88+'Control Panel'!$B$89+'Control Panel'!$B$90)/'Control Panel'!$B$86 -> 81.976604
A9: 0.035 | B9: =(('Unlevered FCF'!E$14/(1+B$4)^1+'Unlevered FCF'!F$14/(1+B$4)^2+'Unlevered FCF'!G$14/(1+B$4)^3+'Unlevered FCF'!H$14/(1+B$4)^4+'Unlevered FCF'!I$14/(1+B$4)^5+'Unlevered FCF'!J$14/(1+B$4)^6)+('Unlevered FCF'!J$14*(1+$A9)/(B$4-$A9))/(1+B$4)^6-'Control Panel'!$B$85-'Control Panel'!$B$87-'Control Panel'!$B$88+'Control Panel'!$B$89+'Control Panel'!$B$90)/'Control Panel'!$B$86 -> 158.8392 | C9: =(('Unlevered FCF'!E$14/(1+C$4)^1+'Unlevered FCF'!F$14/(1+C$4)^2+'Unlevered FCF'!G$14/(1+C$4)^3+'Unlevered FCF'!H$14/(1+C$4)^4+'Unlevered FCF'!I$14/(1+C$4)^5+'Unlevered FCF'!J$14/(1+C$4)^6)+('Unlevered FCF'!J$14*(1+$A9)/(C$4-$A9))/(1+C$4)^6-'Control Panel'!$B$85-'Control Panel'!$B$87-'Control Panel'!$B$88+'Control Panel'!$B$89+'Control Panel'!$B$90)/'Control Panel'!$B$86 -> 140.06927 | D9: =(('Unlevered FCF'!E$14/(1+D$4)^1+'Unlevered FCF'!F$14/(1+D$4)^2+'Unlevered FCF'!G$14/(1+D$4)^3+'Unlevered FCF'!H$14/(1+D$4)^4+'Unlevered FCF'!I$14/(1+D$4)^5+'Unlevered FCF'!J$14/(1+D$4)^6)+('Unlevered FCF'!J$14*(1+$A9)/(D$4-$A9))/(1+D$4)^6-'Control Panel'!$B$85-'Control Panel'!$B$87-'Control Panel'!$B$88+'Control Panel'!$B$89+'Control Panel'!$B$90)/'Control Panel'!$B$86 -> 125.07283 | E9: =(('Unlevered FCF'!E$14/(1+E$4)^1+'Unlevered FCF'!F$14/(1+E$4)^2+'Unlevered FCF'!G$14/(1+E$4)^3+'Unlevered FCF'!H$14/(1+E$4)^4+'Unlevered FCF'!I$14/(1+E$4)^5+'Unlevered FCF'!J$14/(1+E$4)^6)+('Unlevered FCF'!J$14*(1+$A9)/(E$4-$A9))/(1+E$4)^6-'Control Panel'!$B$85-'Control Panel'!$B$87-'Control Panel'!$B$88+'Control Panel'!$B$89+'Control Panel'!$B$90)/'Control Panel'!$B$86 -> 112.82025 | F9: =(('Unlevered FCF'!E$14/(1+F$4)^1+'Unlevered FCF'!F$14/(1+F$4)^2+'Unlevered FCF'!G$14/(1+F$4)^3+'Unlevered FCF'!H$14/(1+F$4)^4+'Unlevered FCF'!I$14/(1+F$4)^5+'Unlevered FCF'!J$14/(1+F$4)^6)+('Unlevered FCF'!J$14*(1+$A9)/(F$4-$A9))/(1+F$4)^6-'Control Panel'!$B$85-'Control Panel'!$B$87-'Control Panel'!$B$88+'Control Panel'!$B$89+'Control Panel'!$B$90)/'Control Panel'!$B$86 -> 102.62516 | G9: =(('Unlevered FCF'!E$14/(1+G$4)^1+'Unlevered FCF'!F$14/(1+G$4)^2+'Unlevered FCF'!G$14/(1+G$4)^3+'Unlevered FCF'!H$14/(1+G$4)^4+'Unlevered FCF'!I$14/(1+G$4)^5+'Unlevered FCF'!J$14/(1+G$4)^6)+('Unlevered FCF'!J$14*(1+$A9)/(G$4-$A9))/(1+G$4)^6-'Control Panel'!$B$85-'Control Panel'!$B$87-'Control Panel'!$B$88+'Control Panel'!$B$89+'Control Panel'!$B$90)/'Control Panel'!$B$86 -> 94.012379 | H9: =(('Unlevered FCF'!E$14/(1+H$4)^1+'Unlevered FCF'!F$14/(1+H$4)^2+'Unlevered FCF'!G$14/(1+H$4)^3+'Unlevered FCF'!H$14/(1+H$4)^4+'Unlevered FCF'!I$14/(1+H$4)^5+'Unlevered FCF'!J$14/(1+H$4)^6)+('Unlevered FCF'!J$14*(1+$A9)/(H$4-$A9))/(1+H$4)^6-'Control Panel'!$B$85-'Control Panel'!$B$87-'Control Panel'!$B$88+'Control Panel'!$B$89+'Control Panel'!$B$90)/'Control Panel'!$B$86 -> 86.642495
A12: Implied share price by WACC and exit multiple
A13: Exit multiple | B13: 0.075 | C13: 0.08 | D13: 0.085 | E13: 0.09 | F13: 0.095 | G13: 0.1 | H13: 0.105
A14: 8.5 | B14: =(('Unlevered FCF'!E$14/(1+B$13)^1+'Unlevered FCF'!F$14/(1+B$13)^2+'Unlevered FCF'!G$14/(1+B$13)^3+'Unlevered FCF'!H$14/(1+B$13)^4+'Unlevered FCF'!I$14/(1+B$13)^5+'Unlevered FCF'!J$14/(1+B$13)^6)+('Margin Cost Build'!J$12*$A14)/(1+B$13)^6-'Control Panel'!$B$85-'Control Panel'!$B$87-'Control Panel'!$B$88+'Control Panel'!$B$89+'Control Panel'!$B$90)/'Control Panel'!$B$86 -> 81.61837 | C14: =(('Unlevered FCF'!E$14/(1+C$13)^1+'Unlevered FCF'!F$14/(1+C$13)^2+'Unlevered FCF'!G$14/(1+C$13)^3+'Unlevered FCF'!H$14/(1+C$13)^4+'Unlevered FCF'!I$14/(1+C$13)^5+'Unlevered FCF'!J$14/(1+C$13)^6)+('Margin Cost Build'!J$12*$A14)/(1+C$13)^6-'Control Panel'!$B$85-'Control Panel'!$B$87-'Control Panel'!$B$88+'Control Panel'!$B$89+'Control Panel'!$B$90)/'Control Panel'!$B$86 -> 79.591596 | D14: =(('Unlevered FCF'!E$14/(1+D$13)^1+'Unlevered FCF'!F$14/(1+D$13)^2+'Unlevered FCF'!G$14/(1+D$13)^3+'Unlevered FCF'!H$14/(1+D$13)^4+'Unlevered FCF'!I$14/(1+D$13)^5+'Unlevered FCF'!J$14/(1+D$13)^6)+('Margin Cost Build'!J$12*$A14)/(1+D$13)^6-'Control Panel'!$B$85-'Control Panel'!$B$87-'Control Panel'!$B$88+'Control Panel'!$B$89+'Control Panel'!$B$90)/'Control Panel'!$B$86 -> 77.626687 | E14: =(('Unlevered FCF'!E$14/(1+E$13)^1+'Unlevered FCF'!F$14/(1+E$13)^2+'Unlevered FCF'!G$14/(1+E$13)^3+'Unlevered FCF'!H$14/(1+E$13)^4+'Unlevered FCF'!I$14/(1+E$13)^5+'Unlevered FCF'!J$14/(1+E$13)^6)+('Margin Cost Build'!J$12*$A14)/(1+E$13)^6-'Control Panel'!$B$85-'Control Panel'!$B$87-'Control Panel'!$B$88+'Control Panel'!$B$89+'Control Panel'!$B$90)/'Control Panel'!$B$86 -> 75.721452 | F14: =(('Unlevered FCF'!E$14/(1+F$13)^1+'Unlevered FCF'!F$14/(1+F$13)^2+'Unlevered FCF'!G$14/(1+F$13)^3+'Unlevered FCF'!H$14/(1+F$13)^4+'Unlevered FCF'!I$14/(1+F$13)^5+'Unlevered FCF'!J$14/(1+F$13)^6)+('Margin Cost Build'!J$12*$A14)/(1+F$13)^6-'Control Panel'!$B$85-'Control Panel'!$B$87-'Control Panel'!$B$88+'Control Panel'!$B$89+'Control Panel'!$B$90)/'Control Panel'!$B$86 -> 73.873786 | G14: =(('Unlevered FCF'!E$14/(1+G$13)^1+'Unlevered FCF'!F$14/(1+G$13)^2+'Unlevered FCF'!G$14/(1+G$13)^3+'Unlevered FCF'!H$14/(1+G$13)^4+'Unlevered FCF'!I$14/(1+G$13)^5+'Unlevered FCF'!J$14/(1+G$13)^6)+('Margin Cost Build'!J$12*$A14)/(1+G$13)^6-'Control Panel'!$B$85-'Control Panel'!$B$87-'Control Panel'!$B$88+'Control Panel'!$B$89+'Control Panel'!$B$90)/'Control Panel'!$B$86 -> 72.081671 | H14: =(('Unlevered FCF'!E$14/(1+H$13)^1+'Unlevered FCF'!F$14/(1+H$13)^2+'Unlevered FCF'!G$14/(1+H$13)^3+'Unlevered FCF'!H$14/(1+H$13)^4+'Unlevered FCF'!I$14/(1+H$13)^5+'Unlevered FCF'!J$14/(1+H$13)^6)+('Margin Cost Build'!J$12*$A14)/(1+H$13)^6-'Control Panel'!$B$85-'Control Panel'!$B$87-'Control Panel'!$B$88+'Control Panel'!$B$89+'Control Panel'!$B$90)/'Control Panel'!$B$86 -> 70.343166
A15: 9.5 | B15: =(('Unlevered FCF'!E$14/(1+B$13)^1+'Unlevered FCF'!F$14/(1+B$13)^2+'Unlevered FCF'!G$14/(1+B$13)^3+'Unlevered FCF'!H$14/(1+B$13)^4+'Unlevered FCF'!I$14/(1+B$13)^5+'Unlevered FCF'!J$14/(1+B$13)^6)+('Margin Cost Build'!J$12*$A15)/(1+B$13)^6-'Control Panel'!$B$85-'Control Panel'!$B$87-'Control Panel'!$B$88+'Control Panel'!$B$89+'Control Panel'!$B$90)/'Control Panel'!$B$86 -> 88.453671 | C15: =(('Unlevered FCF'!E$14/(1+C$13)^1+'Unlevered FCF'!F$14/(1+C$13)^2+'Unlevered FCF'!G$14/(1+C$13)^3+'Unlevered FCF'!H$14/(1+C$13)^4+'Unlevered FCF'!I$14/(1+C$13)^5+'Unlevered FCF'!J$14/(1+C$13)^6)+('Margin Cost Build'!J$12*$A15)/(1+C$13)^6-'Control Panel'!$B$85-'Control Panel'!$B$87-'Control Panel'!$B$88+'Control Panel'!$B$89+'Control Panel'!$B$90)/'Control Panel'!$B$86 -> 86.239212 | D15: =(('Unlevered FCF'!E$14/(1+D$13)^1+'Unlevered FCF'!F$14/(1+D$13)^2+'Unlevered FCF'!G$14/(1+D$13)^3+'Unlevered FCF'!H$14/(1+D$13)^4+'Unlevered FCF'!I$14/(1+D$13)^5+'Unlevered FCF'!J$14/(1+D$13)^6)+('Margin Cost Build'!J$12*$A15)/(1+D$13)^6-'Control Panel'!$B$85-'Control Panel'!$B$87-'Control Panel'!$B$88+'Control Panel'!$B$89+'Control Panel'!$B$90)/'Control Panel'!$B$86 -> 84.092602 | E15: =(('Unlevered FCF'!E$14/(1+E$13)^1+'Unlevered FCF'!F$14/(1+E$13)^2+'Unlevered FCF'!G$14/(1+E$13)^3+'Unlevered FCF'!H$14/(1+E$13)^4+'Unlevered FCF'!I$14/(1+E$13)^5+'Unlevered FCF'!J$14/(1+E$13)^6)+('Margin Cost Build'!J$12*$A15)/(1+E$13)^6-'Control Panel'!$B$85-'Control Panel'!$B$87-'Control Panel'!$B$88+'Control Panel'!$B$89+'Control Panel'!$B$90)/'Control Panel'!$B$86 -> 82.011434 | F15: =(('Unlevered FCF'!E$14/(1+F$13)^1+'Unlevered FCF'!F$14/(1+F$13)^2+'Unlevered FCF'!G$14/(1+F$13)^3+'Unlevered FCF'!H$14/(1+F$13)^4+'Unlevered FCF'!I$14/(1+F$13)^5+'Unlevered FCF'!J$14/(1+F$13)^6)+('Margin Cost Build'!J$12*$A15)/(1+F$13)^6-'Control Panel'!$B$85-'Control Panel'!$B$87-'Control Panel'!$B$88+'Control Panel'!$B$89+'Control Panel'!$B$90)/'Control Panel'!$B$86 -> 79.993396 | G15: =(('Unlevered FCF'!E$14/(1+G$13)^1+'Unlevered FCF'!F$14/(1+G$13)^2+'Unlevered FCF'!G$14/(1+G$13)^3+'Unlevered FCF'!H$14/(1+G$13)^4+'Unlevered FCF'!I$14/(1+G$13)^5+'Unlevered FCF'!J$14/(1+G$13)^6)+('Margin Cost Build'!J$12*$A15)/(1+G$13)^6-'Control Panel'!$B$85-'Control Panel'!$B$87-'Control Panel'!$B$88+'Control Panel'!$B$89+'Control Panel'!$B$90)/'Control Panel'!$B$86 -> 78.036267 | H15: =(('Unlevered FCF'!E$14/(1+H$13)^1+'Unlevered FCF'!F$14/(1+H$13)^2+'Unlevered FCF'!G$14/(1+H$13)^3+'Unlevered FCF'!H$14/(1+H$13)^4+'Unlevered FCF'!I$14/(1+H$13)^5+'Unlevered FCF'!J$14/(1+H$13)^6)+('Margin Cost Build'!J$12*$A15)/(1+H$13)^6-'Control Panel'!$B$85-'Control Panel'!$B$87-'Control Panel'!$B$88+'Control Panel'!$B$89+'Control Panel'!$B$90)/'Control Panel'!$B$86 -> 76.137917
A16: 10.5 | B16: =(('Unlevered FCF'!E$14/(1+B$13)^1+'Unlevered FCF'!F$14/(1+B$13)^2+'Unlevered FCF'!G$14/(1+B$13)^3+'Unlevered FCF'!H$14/(1+B$13)^4+'Unlevered FCF'!I$14/(1+B$13)^5+'Unlevered FCF'!J$14/(1+B$13)^6)+('Margin Cost Build'!J$12*$A16)/(1+B$13)^6-'Control Panel'!$B$85-'Control Panel'!$B$87-'Control Panel'!$B$88+'Control Panel'!$B$89+'Control Panel'!$B$90)/'Control Panel'!$B$86 -> 95.288972 | C16: =(('Unlevered FCF'!E$14/(1+C$13)^1+'Unlevered FCF'!F$14/(1+C$13)^2+'Unlevered FCF'!G$14/(1+C$13)^3+'Unlevered FCF'!H$14/(1+C$13)^4+'Unlevered FCF'!I$14/(1+C$13)^5+'Unlevered FCF'!J$14/(1+C$13)^6)+('Margin Cost Build'!J$12*$A16)/(1+C$13)^6-'Control Panel'!$B$85-'Control Panel'!$B$87-'Control Panel'!$B$88+'Control Panel'!$B$89+'Control Panel'!$B$90)/'Control Panel'!$B$86 -> 92.886827 | D16: =(('Unlevered FCF'!E$14/(1+D$13)^1+'Unlevered FCF'!F$14/(1+D$13)^2+'Unlevered FCF'!G$14/(1+D$13)^3+'Unlevered FCF'!H$14/(1+D$13)^4+'Unlevered FCF'!I$14/(1+D$13)^5+'Unlevered FCF'!J$14/(1+D$13)^6)+('Margin Cost Build'!J$12*$A16)/(1+D$13)^6-'Control Panel'!$B$85-'Control Panel'!$B$87-'Control Panel'!$B$88+'Control Panel'!$B$89+'Control Panel'!$B$90)/'Control Panel'!$B$86 -> 90.558517 | E16: =(('Unlevered FCF'!E$14/(1+E$13)^1+'Unlevered FCF'!F$14/(1+E$13)^2+'Unlevered FCF'!G$14/(1+E$13)^3+'Unlevered FCF'!H$14/(1+E$13)^4+'Unlevered FCF'!I$14/(1+E$13)^5+'Unlevered FCF'!J$14/(1+E$13)^6)+('Margin Cost Build'!J$12*$A16)/(1+E$13)^6-'Control Panel'!$B$85-'Control Panel'!$B$87-'Control Panel'!$B$88+'Control Panel'!$B$89+'Control Panel'!$B$90)/'Control Panel'!$B$86 -> 88.301417 | F16: =(('Unlevered FCF'!E$14/(1+F$13)^1+'Unlevered FCF'!F$14/(1+F$13)^2+'Unlevered FCF'!G$14/(1+F$13)^3+'Unlevered FCF'!H$14/(1+F$13)^4+'Unlevered FCF'!I$14/(1+F$13)^5+'Unlevered FCF'!J$14/(1+F$13)^6)+('Margin Cost Build'!J$12*$A16)/(1+F$13)^6-'Control Panel'!$B$85-'Control Panel'!$B$87-'Control Panel'!$B$88+'Control Panel'!$B$89+'Control Panel'!$B$90)/'Control Panel'!$B$86 -> 86.113005 | G16: =(('Unlevered FCF'!E$14/(1+G$13)^1+'Unlevered FCF'!F$14/(1+G$13)^2+'Unlevered FCF'!G$14/(1+G$13)^3+'Unlevered FCF'!H$14/(1+G$13)^4+'Unlevered FCF'!I$14/(1+G$13)^5+'Unlevered FCF'!J$14/(1+G$13)^6)+('Margin Cost Build'!J$12*$A16)/(1+G$13)^6-'Control Panel'!$B$85-'Control Panel'!$B$87-'Control Panel'!$B$88+'Control Panel'!$B$89+'Control Panel'!$B$90)/'Control Panel'!$B$86 -> 83.990863 | H16: =(('Unlevered FCF'!E$14/(1+H$13)^1+'Unlevered FCF'!F$14/(1+H$13)^2+'Unlevered FCF'!G$14/(1+H$13)^3+'Unlevered FCF'!H$14/(1+H$13)^4+'Unlevered FCF'!I$14/(1+H$13)^5+'Unlevered FCF'!J$14/(1+H$13)^6)+('Margin Cost Build'!J$12*$A16)/(1+H$13)^6-'Control Panel'!$B$85-'Control Panel'!$B$87-'Control Panel'!$B$88+'Control Panel'!$B$89+'Control Panel'!$B$90)/'Control Panel'!$B$86 -> 81.932667
A17: 11.5 | B17: =(('Unlevered FCF'!E$14/(1+B$13)^1+'Unlevered FCF'!F$14/(1+B$13)^2+'Unlevered FCF'!G$14/(1+B$13)^3+'Unlevered FCF'!H$14/(1+B$13)^4+'Unlevered FCF'!I$14/(1+B$13)^5+'Unlevered FCF'!J$14/(1+B$13)^6)+('Margin Cost Build'!J$12*$A17)/(1+B$13)^6-'Control Panel'!$B$85-'Control Panel'!$B$87-'Control Panel'!$B$88+'Control Panel'!$B$89+'Control Panel'!$B$90)/'Control Panel'!$B$86 -> 102.12427 | C17: =(('Unlevered FCF'!E$14/(1+C$13)^1+'Unlevered FCF'!F$14/(1+C$13)^2+'Unlevered FCF'!G$14/(1+C$13)^3+'Unlevered FCF'!H$14/(1+C$13)^4+'Unlevered FCF'!I$14/(1+C$13)^5+'Unlevered FCF'!J$14/(1+C$13)^6)+('Margin Cost Build'!J$12*$A17)/(1+C$13)^6-'Control Panel'!$B$85-'Control Panel'!$B$87-'Control Panel'!$B$88+'Control Panel'!$B$89+'Control Panel'!$B$90)/'Control Panel'!$B$86 -> 99.534443 | D17: =(('Unlevered FCF'!E$14/(1+D$13)^1+'Unlevered FCF'!F$14/(1+D$13)^2+'Unlevered FCF'!G$14/(1+D$13)^3+'Unlevered FCF'!H$14/(1+D$13)^4+'Unlevered FCF'!I$14/(1+D$13)^5+'Unlevered FCF'!J$14/(1+D$13)^6)+('Margin Cost Build'!J$12*$A17)/(1+D$13)^6-'Control Panel'!$B$85-'Control Panel'!$B$87-'Control Panel'!$B$88+'Control Panel'!$B$89+'Control Panel'!$B$90)/'Control Panel'!$B$86 -> 97.024432 | E17: =(('Unlevered FCF'!E$14/(1+E$13)^1+'Unlevered FCF'!F$14/(1+E$13)^2+'Unlevered FCF'!G$14/(1+E$13)^3+'Unlevered FCF'!H$14/(1+E$13)^4+'Unlevered FCF'!I$14/(1+E$13)^5+'Unlevered FCF'!J$14/(1+E$13)^6)+('Margin Cost Build'!J$12*$A17)/(1+E$13)^6-'Control Panel'!$B$85-'Control Panel'!$B$87-'Control Panel'!$B$88+'Control Panel'!$B$89+'Control Panel'!$B$90)/'Control Panel'!$B$86 -> 94.591399 | F17: =(('Unlevered FCF'!E$14/(1+F$13)^1+'Unlevered FCF'!F$14/(1+F$13)^2+'Unlevered FCF'!G$14/(1+F$13)^3+'Unlevered FCF'!H$14/(1+F$13)^4+'Unlevered FCF'!I$14/(1+F$13)^5+'Unlevered FCF'!J$14/(1+F$13)^6)+('Margin Cost Build'!J$12*$A17)/(1+F$13)^6-'Control Panel'!$B$85-'Control Panel'!$B$87-'Control Panel'!$B$88+'Control Panel'!$B$89+'Control Panel'!$B$90)/'Control Panel'!$B$86 -> 92.232614 | G17: =(('Unlevered FCF'!E$14/(1+G$13)^1+'Unlevered FCF'!F$14/(1+G$13)^2+'Unlevered FCF'!G$14/(1+G$13)^3+'Unlevered FCF'!H$14/(1+G$13)^4+'Unlevered FCF'!I$14/(1+G$13)^5+'Unlevered FCF'!J$14/(1+G$13)^6)+('Margin Cost Build'!J$12*$A17)/(1+G$13)^6-'Control Panel'!$B$85-'Control Panel'!$B$87-'Control Panel'!$B$88+'Control Panel'!$B$89+'Control Panel'!$B$90)/'Control Panel'!$B$86 -> 89.945459 | H17: =(('Unlevered FCF'!E$14/(1+H$13)^1+'Unlevered FCF'!F$14/(1+H$13)^2+'Unlevered FCF'!G$14/(1+H$13)^3+'Unlevered FCF'!H$14/(1+H$13)^4+'Unlevered FCF'!I$14/(1+H$13)^5+'Unlevered FCF'!J$14/(1+H$13)^6)+('Margin Cost Build'!J$12*$A17)/(1+H$13)^6-'Control Panel'!$B$85-'Control Panel'!$B$87-'Control Panel'!$B$88+'Control Panel'!$B$89+'Control Panel'!$B$90)/'Control Panel'!$B$86 -> 87.727418
A18: 12.5 | B18: =(('Unlevered FCF'!E$14/(1+B$13)^1+'Unlevered FCF'!F$14/(1+B$13)^2+'Unlevered FCF'!G$14/(1+B$13)^3+'Unlevered FCF'!H$14/(1+B$13)^4+'Unlevered FCF'!I$14/(1+B$13)^5+'Unlevered FCF'!J$14/(1+B$13)^6)+('Margin Cost Build'!J$12*$A18)/(1+B$13)^6-'Control Panel'!$B$85-'Control Panel'!$B$87-'Control Panel'!$B$88+'Control Panel'!$B$89+'Control Panel'!$B$90)/'Control Panel'!$B$86 -> 108.95957 | C18: =(('Unlevered FCF'!E$14/(1+C$13)^1+'Unlevered FCF'!F$14/(1+C$13)^2+'Unlevered FCF'!G$14/(1+C$13)^3+'Unlevered FCF'!H$14/(1+C$13)^4+'Unlevered FCF'!I$14/(1+C$13)^5+'Unlevered FCF'!J$14/(1+C$13)^6)+('Margin Cost Build'!J$12*$A18)/(1+C$13)^6-'Control Panel'!$B$85-'Control Panel'!$B$87-'Control Panel'!$B$88+'Control Panel'!$B$89+'Control Panel'!$B$90)/'Control Panel'!$B$86 -> 106.18206 | D18: =(('Unlevered FCF'!E$14/(1+D$13)^1+'Unlevered FCF'!F$14/(1+D$13)^2+'Unlevered FCF'!G$14/(1+D$13)^3+'Unlevered FCF'!H$14/(1+D$13)^4+'Unlevered FCF'!I$14/(1+D$13)^5+'Unlevered FCF'!J$14/(1+D$13)^6)+('Margin Cost Build'!J$12*$A18)/(1+D$13)^6-'Control Panel'!$B$85-'Control Panel'!$B$87-'Control Panel'!$B$88+'Control Panel'!$B$89+'Control Panel'!$B$90)/'Control Panel'!$B$86 -> 103.49035 | E18: =(('Unlevered FCF'!E$14/(1+E$13)^1+'Unlevered FCF'!F$14/(1+E$13)^2+'Unlevered FCF'!G$14/(1+E$13)^3+'Unlevered FCF'!H$14/(1+E$13)^4+'Unlevered FCF'!I$14/(1+E$13)^5+'Unlevered FCF'!J$14/(1+E$13)^6)+('Margin Cost Build'!J$12*$A18)/(1+E$13)^6-'Control Panel'!$B$85-'Control Panel'!$B$87-'Control Panel'!$B$88+'Control Panel'!$B$89+'Control Panel'!$B$90)/'Control Panel'!$B$86 -> 100.88138 | F18: =(('Unlevered FCF'!E$14/(1+F$13)^1+'Unlevered FCF'!F$14/(1+F$13)^2+'Unlevered FCF'!G$14/(1+F$13)^3+'Unlevered FCF'!H$14/(1+F$13)^4+'Unlevered FCF'!I$14/(1+F$13)^5+'Unlevered FCF'!J$14/(1+F$13)^6)+('Margin Cost Build'!J$12*$A18)/(1+F$13)^6-'Control Panel'!$B$85-'Control Panel'!$B$87-'Control Panel'!$B$88+'Control Panel'!$B$89+'Control Panel'!$B$90)/'Control Panel'!$B$86 -> 98.352224 | G18: =(('Unlevered FCF'!E$14/(1+G$13)^1+'Unlevered FCF'!F$14/(1+G$13)^2+'Unlevered FCF'!G$14/(1+G$13)^3+'Unlevered FCF'!H$14/(1+G$13)^4+'Unlevered FCF'!I$14/(1+G$13)^5+'Unlevered FCF'!J$14/(1+G$13)^6)+('Margin Cost Build'!J$12*$A18)/(1+G$13)^6-'Control Panel'!$B$85-'Control Panel'!$B$87-'Control Panel'!$B$88+'Control Panel'!$B$89+'Control Panel'!$B$90)/'Control Panel'!$B$86 -> 95.900055 | H18: =(('Unlevered FCF'!E$14/(1+H$13)^1+'Unlevered FCF'!F$14/(1+H$13)^2+'Unlevered FCF'!G$14/(1+H$13)^3+'Unlevered FCF'!H$14/(1+H$13)^4+'Unlevered FCF'!I$14/(1+H$13)^5+'Unlevered FCF'!J$14/(1+H$13)^6)+('Margin Cost Build'!J$12*$A18)/(1+H$13)^6-'Control Panel'!$B$85-'Control Panel'!$B$87-'Control Panel'!$B$88+'Control Panel'!$B$89+'Control Panel'!$B$90)/'Control Panel'!$B$86 -> 93.522169
A21: Enterprise value by revenue CAGR and EBITDA margin
A22: EBITDA margin | B22: 0.04 | C22: 0.06 | D22: 0.08 | E22: 0.1 | F22: 0.12 | G22: 0.14 | H22: 0.16
A23: 0.23 | B23: =SUM('Unlevered FCF'!$E$17:$J$17)+(('Revenue Build'!$D$14*(1+B$22)^6)*$A23*'Control Panel'!$B$84)/(1+'Control Panel'!$B$78)^6 -> 59416.303 | C23: =SUM('Unlevered FCF'!$E$17:$J$17)+(('Revenue Build'!$D$14*(1+C$22)^6)*$A23*'Control Panel'!$B$84)/(1+'Control Panel'!$B$78)^6 -> 63687.686 | D23: =SUM('Unlevered FCF'!$E$17:$J$17)+(('Revenue Build'!$D$14*(1+D$22)^6)*$A23*'Control Panel'!$B$84)/(1+'Control Panel'!$B$78)^6 -> 68381.609 | E23: =SUM('Unlevered FCF'!$E$17:$J$17)+(('Revenue Build'!$D$14*(1+E$22)^6)*$A23*'Control Panel'!$B$84)/(1+'Control Panel'!$B$78)^6 -> 73530.872 | F23: =SUM('Unlevered FCF'!$E$17:$J$17)+(('Revenue Build'!$D$14*(1+F$22)^6)*$A23*'Control Panel'!$B$84)/(1+'Control Panel'!$B$78)^6 -> 79170.144 | G23: =SUM('Unlevered FCF'!$E$17:$J$17)+(('Revenue Build'!$D$14*(1+G$22)^6)*$A23*'Control Panel'!$B$84)/(1+'Control Panel'!$B$78)^6 -> 85336.041 | H23: =SUM('Unlevered FCF'!$E$17:$J$17)+(('Revenue Build'!$D$14*(1+H$22)^6)*$A23*'Control Panel'!$B$84)/(1+'Control Panel'!$B$78)^6 -> 92067.193
A24: 0.25 | B24: =SUM('Unlevered FCF'!$E$17:$J$17)+(('Revenue Build'!$D$14*(1+B$22)^6)*$A24*'Control Panel'!$B$84)/(1+'Control Panel'!$B$78)^6 -> 62483.994 | C24: =SUM('Unlevered FCF'!$E$17:$J$17)+(('Revenue Build'!$D$14*(1+C$22)^6)*$A24*'Control Panel'!$B$84)/(1+'Control Panel'!$B$78)^6 -> 67126.802 | D24: =SUM('Unlevered FCF'!$E$17:$J$17)+(('Revenue Build'!$D$14*(1+D$22)^6)*$A24*'Control Panel'!$B$84)/(1+'Control Panel'!$B$78)^6 -> 72228.892 | E24: =SUM('Unlevered FCF'!$E$17:$J$17)+(('Revenue Build'!$D$14*(1+E$22)^6)*$A24*'Control Panel'!$B$84)/(1+'Control Panel'!$B$78)^6 -> 77825.917 | F24: =SUM('Unlevered FCF'!$E$17:$J$17)+(('Revenue Build'!$D$14*(1+F$22)^6)*$A24*'Control Panel'!$B$84)/(1+'Control Panel'!$B$78)^6 -> 83955.561 | G24: =SUM('Unlevered FCF'!$E$17:$J$17)+(('Revenue Build'!$D$14*(1+G$22)^6)*$A24*'Control Panel'!$B$84)/(1+'Control Panel'!$B$78)^6 -> 90657.623 | H24: =SUM('Unlevered FCF'!$E$17:$J$17)+(('Revenue Build'!$D$14*(1+H$22)^6)*$A24*'Control Panel'!$B$84)/(1+'Control Panel'!$B$78)^6 -> 97974.092
A25: 0.27 | B25: =SUM('Unlevered FCF'!$E$17:$J$17)+(('Revenue Build'!$D$14*(1+B$22)^6)*$A25*'Control Panel'!$B$84)/(1+'Control Panel'!$B$78)^6 -> 65551.686 | C25: =SUM('Unlevered FCF'!$E$17:$J$17)+(('Revenue Build'!$D$14*(1+C$22)^6)*$A25*'Control Panel'!$B$84)/(1+'Control Panel'!$B$78)^6 -> 70565.917 | D25: =SUM('Unlevered FCF'!$E$17:$J$17)+(('Revenue Build'!$D$14*(1+D$22)^6)*$A25*'Control Panel'!$B$84)/(1+'Control Panel'!$B$78)^6 -> 76076.176 | E25: =SUM('Unlevered FCF'!$E$17:$J$17)+(('Revenue Build'!$D$14*(1+E$22)^6)*$A25*'Control Panel'!$B$84)/(1+'Control Panel'!$B$78)^6 -> 82120.962 | F25: =SUM('Unlevered FCF'!$E$17:$J$17)+(('Revenue Build'!$D$14*(1+F$22)^6)*$A25*'Control Panel'!$B$84)/(1+'Control Panel'!$B$78)^6 -> 88740.977 | G25: =SUM('Unlevered FCF'!$E$17:$J$17)+(('Revenue Build'!$D$14*(1+G$22)^6)*$A25*'Control Panel'!$B$84)/(1+'Control Panel'!$B$78)^6 -> 95979.204 | H25: =SUM('Unlevered FCF'!$E$17:$J$17)+(('Revenue Build'!$D$14*(1+H$22)^6)*$A25*'Control Panel'!$B$84)/(1+'Control Panel'!$B$78)^6 -> 103880.99
A26: 0.29 | B26: =SUM('Unlevered FCF'!$E$17:$J$17)+(('Revenue Build'!$D$14*(1+B$22)^6)*$A26*'Control Panel'!$B$84)/(1+'Control Panel'!$B$78)^6 -> 68619.377 | C26: =SUM('Unlevered FCF'!$E$17:$J$17)+(('Revenue Build'!$D$14*(1+C$22)^6)*$A26*'Control Panel'!$B$84)/(1+'Control Panel'!$B$78)^6 -> 74005.033 | D26: =SUM('Unlevered FCF'!$E$17:$J$17)+(('Revenue Build'!$D$14*(1+D$22)^6)*$A26*'Control Panel'!$B$84)/(1+'Control Panel'!$B$78)^6 -> 79923.459 | E26: =SUM('Unlevered FCF'!$E$17:$J$17)+(('Revenue Build'!$D$14*(1+E$22)^6)*$A26*'Control Panel'!$B$84)/(1+'Control Panel'!$B$78)^6 -> 86416.007 | F26: =SUM('Unlevered FCF'!$E$17:$J$17)+(('Revenue Build'!$D$14*(1+F$22)^6)*$A26*'Control Panel'!$B$84)/(1+'Control Panel'!$B$78)^6 -> 93526.394 | G26: =SUM('Unlevered FCF'!$E$17:$J$17)+(('Revenue Build'!$D$14*(1+G$22)^6)*$A26*'Control Panel'!$B$84)/(1+'Control Panel'!$B$78)^6 -> 101300.79 | H26: =SUM('Unlevered FCF'!$E$17:$J$17)+(('Revenue Build'!$D$14*(1+H$22)^6)*$A26*'Control Panel'!$B$84)/(1+'Control Panel'!$B$78)^6 -> 109787.89
A27: 0.31 | B27: =SUM('Unlevered FCF'!$E$17:$J$17)+(('Revenue Build'!$D$14*(1+B$22)^6)*$A27*'Control Panel'!$B$84)/(1+'Control Panel'!$B$78)^6 -> 71687.068 | C27: =SUM('Unlevered FCF'!$E$17:$J$17)+(('Revenue Build'!$D$14*(1+C$22)^6)*$A27*'Control Panel'!$B$84)/(1+'Control Panel'!$B$78)^6 -> 77444.149 | D27: =SUM('Unlevered FCF'!$E$17:$J$17)+(('Revenue Build'!$D$14*(1+D$22)^6)*$A27*'Control Panel'!$B$84)/(1+'Control Panel'!$B$78)^6 -> 83770.742 | E27: =SUM('Unlevered FCF'!$E$17:$J$17)+(('Revenue Build'!$D$14*(1+E$22)^6)*$A27*'Control Panel'!$B$84)/(1+'Control Panel'!$B$78)^6 -> 90711.052 | F27: =SUM('Unlevered FCF'!$E$17:$J$17)+(('Revenue Build'!$D$14*(1+F$22)^6)*$A27*'Control Panel'!$B$84)/(1+'Control Panel'!$B$78)^6 -> 98311.81 | G27: =SUM('Unlevered FCF'!$E$17:$J$17)+(('Revenue Build'!$D$14*(1+G$22)^6)*$A27*'Control Panel'!$B$84)/(1+'Control Panel'!$B$78)^6 -> 106622.37 | H27: =SUM('Unlevered FCF'!$E$17:$J$17)+(('Revenue Build'!$D$14*(1+H$22)^6)*$A27*'Control Panel'!$B$84)/(1+'Control Panel'!$B$78)^6 -> 115694.79
A30: Equity value by WACC and terminal growth
A31: Terminal growth | B31: 0.075 | C31: 0.08 | D31: 0.085 | E31: 0.09 | F31: 0.095 | G31: 0.1 | H31: 0.105
A32: 0.015 | B32: =(('Unlevered FCF'!E$14/(1+B$31)^1+'Unlevered FCF'!F$14/(1+B$31)^2+'Unlevered FCF'!G$14/(1+B$31)^3+'Unlevered FCF'!H$14/(1+B$31)^4+'Unlevered FCF'!I$14/(1+B$31)^5+'Unlevered FCF'!J$14/(1+B$31)^6)+('Unlevered FCF'!J$14*(1+$A32)/(B$31-$A32))/(1+B$31)^6-'Control Panel'!$B$85-'Control Panel'!$B$87-'Control Panel'!$B$88+'Control Panel'!$B$89+'Control Panel'!$B$90) -> 115796.6 | C32: =(('Unlevered FCF'!E$14/(1+C$31)^1+'Unlevered FCF'!F$14/(1+C$31)^2+'Unlevered FCF'!G$14/(1+C$31)^3+'Unlevered FCF'!H$14/(1+C$31)^4+'Unlevered FCF'!I$14/(1+C$31)^5+'Unlevered FCF'!J$14/(1+C$31)^6)+('Unlevered FCF'!J$14*(1+$A32)/(C$31-$A32))/(1+C$31)^6-'Control Panel'!$B$85-'Control Panel'!$B$87-'Control Panel'!$B$88+'Control Panel'!$B$89+'Control Panel'!$B$90) -> 105995.03 | D32: =(('Unlevered FCF'!E$14/(1+D$31)^1+'Unlevered FCF'!F$14/(1+D$31)^2+'Unlevered FCF'!G$14/(1+D$31)^3+'Unlevered FCF'!H$14/(1+D$31)^4+'Unlevered FCF'!I$14/(1+D$31)^5+'Unlevered FCF'!J$14/(1+D$31)^6)+('Unlevered FCF'!J$14*(1+$A32)/(D$31-$A32))/(1+D$31)^6-'Control Panel'!$B$85-'Control Panel'!$B$87-'Control Panel'!$B$88+'Control Panel'!$B$89+'Control Panel'!$B$90) -> 97609.986 | E32: =(('Unlevered FCF'!E$14/(1+E$31)^1+'Unlevered FCF'!F$14/(1+E$31)^2+'Unlevered FCF'!G$14/(1+E$31)^3+'Unlevered FCF'!H$14/(1+E$31)^4+'Unlevered FCF'!I$14/(1+E$31)^5+'Unlevered FCF'!J$14/(1+E$31)^6)+('Unlevered FCF'!J$14*(1+$A32)/(E$31-$A32))/(1+E$31)^6-'Control Panel'!$B$85-'Control Panel'!$B$87-'Control Panel'!$B$88+'Control Panel'!$B$89+'Control Panel'!$B$90) -> 90357.74 | F32: =(('Unlevered FCF'!E$14/(1+F$31)^1+'Unlevered FCF'!F$14/(1+F$31)^2+'Unlevered FCF'!G$14/(1+F$31)^3+'Unlevered FCF'!H$14/(1+F$31)^4+'Unlevered FCF'!I$14/(1+F$31)^5+'Unlevered FCF'!J$14/(1+F$31)^6)+('Unlevered FCF'!J$14*(1+$A32)/(F$31-$A32))/(1+F$31)^6-'Control Panel'!$B$85-'Control Panel'!$B$87-'Control Panel'!$B$88+'Control Panel'!$B$89+'Control Panel'!$B$90) -> 84025.526 | G32: =(('Unlevered FCF'!E$14/(1+G$31)^1+'Unlevered FCF'!F$14/(1+G$31)^2+'Unlevered FCF'!G$14/(1+G$31)^3+'Unlevered FCF'!H$14/(1+G$31)^4+'Unlevered FCF'!I$14/(1+G$31)^5+'Unlevered FCF'!J$14/(1+G$31)^6)+('Unlevered FCF'!J$14*(1+$A32)/(G$31-$A32))/(1+G$31)^6-'Control Panel'!$B$85-'Control Panel'!$B$87-'Control Panel'!$B$88+'Control Panel'!$B$89+'Control Panel'!$B$90) -> 78450.646 | H32: =(('Unlevered FCF'!E$14/(1+H$31)^1+'Unlevered FCF'!F$14/(1+H$31)^2+'Unlevered FCF'!G$14/(1+H$31)^3+'Unlevered FCF'!H$14/(1+H$31)^4+'Unlevered FCF'!I$14/(1+H$31)^5+'Unlevered FCF'!J$14/(1+H$31)^6)+('Unlevered FCF'!J$14*(1+$A32)/(H$31-$A32))/(1+H$31)^6-'Control Panel'!$B$85-'Control Panel'!$B$87-'Control Panel'!$B$88+'Control Panel'!$B$89+'Control Panel'!$B$90) -> 73506.57
A33: 0.02 | B33: =(('Unlevered FCF'!E$14/(1+B$31)^1+'Unlevered FCF'!F$14/(1+B$31)^2+'Unlevered FCF'!G$14/(1+B$31)^3+'Unlevered FCF'!H$14/(1+B$31)^4+'Unlevered FCF'!I$14/(1+B$31)^5+'Unlevered FCF'!J$14/(1+B$31)^6)+('Unlevered FCF'!J$14*(1+$A33)/(B$31-$A33))/(1+B$31)^6-'Control Panel'!$B$85-'Control Panel'!$B$87-'Control Panel'!$B$88+'Control Panel'!$B$89+'Control Panel'!$B$90) -> 124604.44 | C33: =(('Unlevered FCF'!E$14/(1+C$31)^1+'Unlevered FCF'!F$14/(1+C$31)^2+'Unlevered FCF'!G$14/(1+C$31)^3+'Unlevered FCF'!H$14/(1+C$31)^4+'Unlevered FCF'!I$14/(1+C$31)^5+'Unlevered FCF'!J$14/(1+C$31)^6)+('Unlevered FCF'!J$14*(1+$A33)/(C$31-$A33))/(1+C$31)^6-'Control Panel'!$B$85-'Control Panel'!$B$87-'Control Panel'!$B$88+'Control Panel'!$B$89+'Control Panel'!$B$90) -> 113276.9 | D33: =(('Unlevered FCF'!E$14/(1+D$31)^1+'Unlevered FCF'!F$14/(1+D$31)^2+'Unlevered FCF'!G$14/(1+D$31)^3+'Unlevered FCF'!H$14/(1+D$31)^4+'Unlevered FCF'!I$14/(1+D$31)^5+'Unlevered FCF'!J$14/(1+D$31)^6)+('Unlevered FCF'!J$14*(1+$A33)/(D$31-$A33))/(1+D$31)^6-'Control Panel'!$B$85-'Control Panel'!$B$87-'Control Panel'!$B$88+'Control Panel'!$B$89+'Control Panel'!$B$90) -> 103709.09 | E33: =(('Unlevered FCF'!E$14/(1+E$31)^1+'Unlevered FCF'!F$14/(1+E$31)^2+'Unlevered FCF'!G$14/(1+E$31)^3+'Unlevered FCF'!H$14/(1+E$31)^4+'Unlevered FCF'!I$14/(1+E$31)^5+'Unlevered FCF'!J$14/(1+E$31)^6)+('Unlevered FCF'!J$14*(1+$A33)/(E$31-$A33))/(1+E$31)^6-'Control Panel'!$B$85-'Control Panel'!$B$87-'Control Panel'!$B$88+'Control Panel'!$B$89+'Control Panel'!$B$90) -> 95523.498 | F33: =(('Unlevered FCF'!E$14/(1+F$31)^1+'Unlevered FCF'!F$14/(1+F$31)^2+'Unlevered FCF'!G$14/(1+F$31)^3+'Unlevered FCF'!H$14/(1+F$31)^4+'Unlevered FCF'!I$14/(1+F$31)^5+'Unlevered FCF'!J$14/(1+F$31)^6)+('Unlevered FCF'!J$14*(1+$A33)/(F$31-$A33))/(1+F$31)^6-'Control Panel'!$B$85-'Control Panel'!$B$87-'Control Panel'!$B$88+'Control Panel'!$B$89+'Control Panel'!$B$90) -> 88443.305 | G33: =(('Unlevered FCF'!E$14/(1+G$31)^1+'Unlevered FCF'!F$14/(1+G$31)^2+'Unlevered FCF'!G$14/(1+G$31)^3+'Unlevered FCF'!H$14/(1+G$31)^4+'Unlevered FCF'!I$14/(1+G$31)^5+'Unlevered FCF'!J$14/(1+G$31)^6)+('Unlevered FCF'!J$14*(1+$A33)/(G$31-$A33))/(1+G$31)^6-'Control Panel'!$B$85-'Control Panel'!$B$87-'Control Panel'!$B$88+'Control Panel'!$B$89+'Control Panel'!$B$90) -> 82260.896 | H33: =(('Unlevered FCF'!E$14/(1+H$31)^1+'Unlevered FCF'!F$14/(1+H$31)^2+'Unlevered FCF'!G$14/(1+H$31)^3+'Unlevered FCF'!H$14/(1+H$31)^4+'Unlevered FCF'!I$14/(1+H$31)^5+'Unlevered FCF'!J$14/(1+H$31)^6)+('Unlevered FCF'!J$14*(1+$A33)/(H$31-$A33))/(1+H$31)^6-'Control Panel'!$B$85-'Control Panel'!$B$87-'Control Panel'!$B$88+'Control Panel'!$B$89+'Control Panel'!$B$90) -> 76817.522
A34: 0.025 | B34: =(('Unlevered FCF'!E$14/(1+B$31)^1+'Unlevered FCF'!F$14/(1+B$31)^2+'Unlevered FCF'!G$14/(1+B$31)^3+'Unlevered FCF'!H$14/(1+B$31)^4+'Unlevered FCF'!I$14/(1+B$31)^5+'Unlevered FCF'!J$14/(1+B$31)^6)+('Unlevered FCF'!J$14*(1+$A34)/(B$31-$A34))/(1+B$31)^6-'Control Panel'!$B$85-'Control Panel'!$B$87-'Control Panel'!$B$88+'Control Panel'!$B$89+'Control Panel'!$B$90) -> 135173.85 | C34: =(('Unlevered FCF'!E$14/(1+C$31)^1+'Unlevered FCF'!F$14/(1+C$31)^2+'Unlevered FCF'!G$14/(1+C$31)^3+'Unlevered FCF'!H$14/(1+C$31)^4+'Unlevered FCF'!I$14/(1+C$31)^5+'Unlevered FCF'!J$14/(1+C$31)^6)+('Unlevered FCF'!J$14*(1+$A34)/(C$31-$A34))/(1+C$31)^6-'Control Panel'!$B$85-'Control Panel'!$B$87-'Control Panel'!$B$88+'Control Panel'!$B$89+'Control Panel'!$B$90) -> 121882.73 | D34: =(('Unlevered FCF'!E$14/(1+D$31)^1+'Unlevered FCF'!F$14/(1+D$31)^2+'Unlevered FCF'!G$14/(1+D$31)^3+'Unlevered FCF'!H$14/(1+D$31)^4+'Unlevered FCF'!I$14/(1+D$31)^5+'Unlevered FCF'!J$14/(1+D$31)^6)+('Unlevered FCF'!J$14*(1+$A34)/(D$31-$A34))/(1+D$31)^6-'Control Panel'!$B$85-'Control Panel'!$B$87-'Control Panel'!$B$88+'Control Panel'!$B$89+'Control Panel'!$B$90) -> 110824.7 | E34: =(('Unlevered FCF'!E$14/(1+E$31)^1+'Unlevered FCF'!F$14/(1+E$31)^2+'Unlevered FCF'!G$14/(1+E$31)^3+'Unlevered FCF'!H$14/(1+E$31)^4+'Unlevered FCF'!I$14/(1+E$31)^5+'Unlevered FCF'!J$14/(1+E$31)^6)+('Unlevered FCF'!J$14*(1+$A34)/(E$31-$A34))/(1+E$31)^6-'Control Panel'!$B$85-'Control Panel'!$B$87-'Control Panel'!$B$88+'Control Panel'!$B$89+'Control Panel'!$B$90) -> 101483.99 | F34: =(('Unlevered FCF'!E$14/(1+F$31)^1+'Unlevered FCF'!F$14/(1+F$31)^2+'Unlevered FCF'!G$14/(1+F$31)^3+'Unlevered FCF'!H$14/(1+F$31)^4+'Unlevered FCF'!I$14/(1+F$31)^5+'Unlevered FCF'!J$14/(1+F$31)^6)+('Unlevered FCF'!J$14*(1+$A34)/(F$31-$A34))/(1+F$31)^6-'Control Panel'!$B$85-'Control Panel'!$B$87-'Control Panel'!$B$88+'Control Panel'!$B$89+'Control Panel'!$B$90) -> 93492.195 | G34: =(('Unlevered FCF'!E$14/(1+G$31)^1+'Unlevered FCF'!F$14/(1+G$31)^2+'Unlevered FCF'!G$14/(1+G$31)^3+'Unlevered FCF'!H$14/(1+G$31)^4+'Unlevered FCF'!I$14/(1+G$31)^5+'Unlevered FCF'!J$14/(1+G$31)^6)+('Unlevered FCF'!J$14*(1+$A34)/(G$31-$A34))/(1+G$31)^6-'Control Panel'!$B$85-'Control Panel'!$B$87-'Control Panel'!$B$88+'Control Panel'!$B$89+'Control Panel'!$B$90) -> 86579.179 | H34: =(('Unlevered FCF'!E$14/(1+H$31)^1+'Unlevered FCF'!F$14/(1+H$31)^2+'Unlevered FCF'!G$14/(1+H$31)^3+'Unlevered FCF'!H$14/(1+H$31)^4+'Unlevered FCF'!I$14/(1+H$31)^5+'Unlevered FCF'!J$14/(1+H$31)^6)+('Unlevered FCF'!J$14*(1+$A34)/(H$31-$A34))/(1+H$31)^6-'Control Panel'!$B$85-'Control Panel'!$B$87-'Control Panel'!$B$88+'Control Panel'!$B$89+'Control Panel'!$B$90) -> 80542.344
A35: 0.03 | B35: =(('Unlevered FCF'!E$14/(1+B$31)^1+'Unlevered FCF'!F$14/(1+B$31)^2+'Unlevered FCF'!G$14/(1+B$31)^3+'Unlevered FCF'!H$14/(1+B$31)^4+'Unlevered FCF'!I$14/(1+B$31)^5+'Unlevered FCF'!J$14/(1+B$31)^6)+('Unlevered FCF'!J$14*(1+$A35)/(B$31-$A35))/(1+B$31)^6-'Control Panel'!$B$85-'Control Panel'!$B$87-'Control Panel'!$B$88+'Control Panel'!$B$89+'Control Panel'!$B$90) -> 148092.02 | C35: =(('Unlevered FCF'!E$14/(1+C$31)^1+'Unlevered FCF'!F$14/(1+C$31)^2+'Unlevered FCF'!G$14/(1+C$31)^3+'Unlevered FCF'!H$14/(1+C$31)^4+'Unlevered FCF'!I$14/(1+C$31)^5+'Unlevered FCF'!J$14/(1+C$31)^6)+('Unlevered FCF'!J$14*(1+$A35)/(C$31-$A35))/(1+C$31)^6-'Control Panel'!$B$85-'Control Panel'!$B$87-'Control Panel'!$B$88+'Control Panel'!$B$89+'Control Panel'!$B$90) -> 132209.74 | D35: =(('Unlevered FCF'!E$14/(1+D$31)^1+'Unlevered FCF'!F$14/(1+D$31)^2+'Unlevered FCF'!G$14/(1+D$31)^3+'Unlevered FCF'!H$14/(1+D$31)^4+'Unlevered FCF'!I$14/(1+D$31)^5+'Unlevered FCF'!J$14/(1+D$31)^6)+('Unlevered FCF'!J$14*(1+$A35)/(D$31-$A35))/(1+D$31)^6-'Control Panel'!$B$85-'Control Panel'!$B$87-'Control Panel'!$B$88+'Control Panel'!$B$89+'Control Panel'!$B$90) -> 119234.07 | E35: =(('Unlevered FCF'!E$14/(1+E$31)^1+'Unlevered FCF'!F$14/(1+E$31)^2+'Unlevered FCF'!G$14/(1+E$31)^3+'Unlevered FCF'!H$14/(1+E$31)^4+'Unlevered FCF'!I$14/(1+E$31)^5+'Unlevered FCF'!J$14/(1+E$31)^6)+('Unlevered FCF'!J$14*(1+$A35)/(E$31-$A35))/(1+E$31)^6-'Control Panel'!$B$85-'Control Panel'!$B$87-'Control Panel'!$B$88+'Control Panel'!$B$89+'Control Panel'!$B$90) -> 108437.89 | F35: =(('Unlevered FCF'!E$14/(1+F$31)^1+'Unlevered FCF'!F$14/(1+F$31)^2+'Unlevered FCF'!G$14/(1+F$31)^3+'Unlevered FCF'!H$14/(1+F$31)^4+'Unlevered FCF'!I$14/(1+F$31)^5+'Unlevered FCF'!J$14/(1+F$31)^6)+('Unlevered FCF'!J$14*(1+$A35)/(F$31-$A35))/(1+F$31)^6-'Control Panel'!$B$85-'Control Panel'!$B$87-'Control Panel'!$B$88+'Control Panel'!$B$89+'Control Panel'!$B$90) -> 99317.837 | G35: =(('Unlevered FCF'!E$14/(1+G$31)^1+'Unlevered FCF'!F$14/(1+G$31)^2+'Unlevered FCF'!G$14/(1+G$31)^3+'Unlevered FCF'!H$14/(1+G$31)^4+'Unlevered FCF'!I$14/(1+G$31)^5+'Unlevered FCF'!J$14/(1+G$31)^6)+('Unlevered FCF'!J$14*(1+$A35)/(G$31-$A35))/(1+G$31)^6-'Control Panel'!$B$85-'Control Panel'!$B$87-'Control Panel'!$B$88+'Control Panel'!$B$89+'Control Panel'!$B$90) -> 91514.36 | H35: =(('Unlevered FCF'!E$14/(1+H$31)^1+'Unlevered FCF'!F$14/(1+H$31)^2+'Unlevered FCF'!G$14/(1+H$31)^3+'Unlevered FCF'!H$14/(1+H$31)^4+'Unlevered FCF'!I$14/(1+H$31)^5+'Unlevered FCF'!J$14/(1+H$31)^6)+('Unlevered FCF'!J$14*(1+$A35)/(H$31-$A35))/(1+H$31)^6-'Control Panel'!$B$85-'Control Panel'!$B$87-'Control Panel'!$B$88+'Control Panel'!$B$89+'Control Panel'!$B$90) -> 84763.809
A36: 0.035 | B36: =(('Unlevered FCF'!E$14/(1+B$31)^1+'Unlevered FCF'!F$14/(1+B$31)^2+'Unlevered FCF'!G$14/(1+B$31)^3+'Unlevered FCF'!H$14/(1+B$31)^4+'Unlevered FCF'!I$14/(1+B$31)^5+'Unlevered FCF'!J$14/(1+B$31)^6)+('Unlevered FCF'!J$14*(1+$A36)/(B$31-$A36))/(1+B$31)^6-'Control Panel'!$B$85-'Control Panel'!$B$87-'Control Panel'!$B$88+'Control Panel'!$B$89+'Control Panel'!$B$90) -> 164239.73 | C36: =(('Unlevered FCF'!E$14/(1+C$31)^1+'Unlevered FCF'!F$14/(1+C$31)^2+'Unlevered FCF'!G$14/(1+C$31)^3+'Unlevered FCF'!H$14/(1+C$31)^4+'Unlevered FCF'!I$14/(1+C$31)^5+'Unlevered FCF'!J$14/(1+C$31)^6)+('Unlevered FCF'!J$14*(1+$A36)/(C$31-$A36))/(1+C$31)^6-'Control Panel'!$B$85-'Control Panel'!$B$87-'Control Panel'!$B$88+'Control Panel'!$B$89+'Control Panel'!$B$90) -> 144831.63 | D36: =(('Unlevered FCF'!E$14/(1+D$31)^1+'Unlevered FCF'!F$14/(1+D$31)^2+'Unlevered FCF'!G$14/(1+D$31)^3+'Unlevered FCF'!H$14/(1+D$31)^4+'Unlevered FCF'!I$14/(1+D$31)^5+'Unlevered FCF'!J$14/(1+D$31)^6)+('Unlevered FCF'!J$14*(1+$A36)/(D$31-$A36))/(1+D$31)^6-'Control Panel'!$B$85-'Control Panel'!$B$87-'Control Panel'!$B$88+'Control Panel'!$B$89+'Control Panel'!$B$90) -> 129325.3 | E36: =(('Unlevered FCF'!E$14/(1+E$31)^1+'Unlevered FCF'!F$14/(1+E$31)^2+'Unlevered FCF'!G$14/(1+E$31)^3+'Unlevered FCF'!H$14/(1+E$31)^4+'Unlevered FCF'!I$14/(1+E$31)^5+'Unlevered FCF'!J$14/(1+E$31)^6)+('Unlevered FCF'!J$14*(1+$A36)/(E$31-$A36))/(1+E$31)^6-'Control Panel'!$B$85-'Control Panel'!$B$87-'Control Panel'!$B$88+'Control Panel'!$B$89+'Control Panel'!$B$90) -> 116656.14 | F36: =(('Unlevered FCF'!E$14/(1+F$31)^1+'Unlevered FCF'!F$14/(1+F$31)^2+'Unlevered FCF'!G$14/(1+F$31)^3+'Unlevered FCF'!H$14/(1+F$31)^4+'Unlevered FCF'!I$14/(1+F$31)^5+'Unlevered FCF'!J$14/(1+F$31)^6)+('Unlevered FCF'!J$14*(1+$A36)/(F$31-$A36))/(1+F$31)^6-'Control Panel'!$B$85-'Control Panel'!$B$87-'Control Panel'!$B$88+'Control Panel'!$B$89+'Control Panel'!$B$90) -> 106114.42 | G36: =(('Unlevered FCF'!E$14/(1+G$31)^1+'Unlevered FCF'!F$14/(1+G$31)^2+'Unlevered FCF'!G$14/(1+G$31)^3+'Unlevered FCF'!H$14/(1+G$31)^4+'Unlevered FCF'!I$14/(1+G$31)^5+'Unlevered FCF'!J$14/(1+G$31)^6)+('Unlevered FCF'!J$14*(1+$A36)/(G$31-$A36))/(1+G$31)^6-'Control Panel'!$B$85-'Control Panel'!$B$87-'Control Panel'!$B$88+'Control Panel'!$B$89+'Control Panel'!$B$90) -> 97208.8 | H36: =(('Unlevered FCF'!E$14/(1+H$31)^1+'Unlevered FCF'!F$14/(1+H$31)^2+'Unlevered FCF'!G$14/(1+H$31)^3+'Unlevered FCF'!H$14/(1+H$31)^4+'Unlevered FCF'!I$14/(1+H$31)^5+'Unlevered FCF'!J$14/(1+H$31)^6)+('Unlevered FCF'!J$14*(1+$A36)/(H$31-$A36))/(1+H$31)^6-'Control Panel'!$B$85-'Control Panel'!$B$87-'Control Panel'!$B$88+'Control Panel'!$B$89+'Control Panel'!$B$90) -> 89588.34
A39: Upside / downside by WACC and terminal growth
A40: Terminal growth | B40: 0.075 | C40: 0.08 | D40: 0.085 | E40: 0.09 | F40: 0.095 | G40: 0.1 | H40: 0.105
A41: 0.015 | B41: =(('Unlevered FCF'!E$14/(1+B$40)^1+'Unlevered FCF'!F$14/(1+B$40)^2+'Unlevered FCF'!G$14/(1+B$40)^3+'Unlevered FCF'!H$14/(1+B$40)^4+'Unlevered FCF'!I$14/(1+B$40)^5+'Unlevered FCF'!J$14/(1+B$40)^6)+('Unlevered FCF'!J$14*(1+$A41)/(B$40-$A41))/(1+B$40)^6-'Control Panel'!$B$85-'Control Panel'!$B$87-'Control Panel'!$B$88+'Control Panel'!$B$89+'Control Panel'!$B$90)/'Control Panel'!$B$86/'Control Panel'!$B$12-1 -> 0.15037464 | C41: =(('Unlevered FCF'!E$14/(1+C$40)^1+'Unlevered FCF'!F$14/(1+C$40)^2+'Unlevered FCF'!G$14/(1+C$40)^3+'Unlevered FCF'!H$14/(1+C$40)^4+'Unlevered FCF'!I$14/(1+C$40)^5+'Unlevered FCF'!J$14/(1+C$40)^6)+('Unlevered FCF'!J$14*(1+$A41)/(C$40-$A41))/(1+C$40)^6-'Control Panel'!$B$85-'Control Panel'!$B$87-'Control Panel'!$B$88+'Control Panel'!$B$89+'Control Panel'!$B$90)/'Control Panel'!$B$86/'Control Panel'!$B$12-1 -> 0.053001582 | D41: =(('Unlevered FCF'!E$14/(1+D$40)^1+'Unlevered FCF'!F$14/(1+D$40)^2+'Unlevered FCF'!G$14/(1+D$40)^3+'Unlevered FCF'!H$14/(1+D$40)^4+'Unlevered FCF'!I$14/(1+D$40)^5+'Unlevered FCF'!J$14/(1+D$40)^6)+('Unlevered FCF'!J$14*(1+$A41)/(D$40-$A41))/(1+D$40)^6-'Control Panel'!$B$85-'Control Panel'!$B$87-'Control Panel'!$B$88+'Control Panel'!$B$89+'Control Panel'!$B$90)/'Control Panel'!$B$86/'Control Panel'!$B$12-1 -> -0.030299197 | E41: =(('Unlevered FCF'!E$14/(1+E$40)^1+'Unlevered FCF'!F$14/(1+E$40)^2+'Unlevered FCF'!G$14/(1+E$40)^3+'Unlevered FCF'!H$14/(1+E$40)^4+'Unlevered FCF'!I$14/(1+E$40)^5+'Unlevered FCF'!J$14/(1+E$40)^6)+('Unlevered FCF'!J$14*(1+$A41)/(E$40-$A41))/(1+E$40)^6-'Control Panel'!$B$85-'Control Panel'!$B$87-'Control Panel'!$B$88+'Control Panel'!$B$89+'Control Panel'!$B$90)/'Control Panel'!$B$86/'Control Panel'!$B$12-1 -> -0.10234621 | F41: =(('Unlevered FCF'!E$14/(1+F$40)^1+'Unlevered FCF'!F$14/(1+F$40)^2+'Unlevered FCF'!G$14/(1+F$40)^3+'Unlevered FCF'!H$14/(1+F$40)^4+'Unlevered FCF'!I$14/(1+F$40)^5+'Unlevered FCF'!J$14/(1+F$40)^6)+('Unlevered FCF'!J$14*(1+$A41)/(F$40-$A41))/(1+F$40)^6-'Control Panel'!$B$85-'Control Panel'!$B$87-'Control Panel'!$B$88+'Control Panel'!$B$89+'Control Panel'!$B$90)/'Control Panel'!$B$86/'Control Panel'!$B$12-1 -> -0.16525323 | G41: =(('Unlevered FCF'!E$14/(1+G$40)^1+'Unlevered FCF'!F$14/(1+G$40)^2+'Unlevered FCF'!G$14/(1+G$40)^3+'Unlevered FCF'!H$14/(1+G$40)^4+'Unlevered FCF'!I$14/(1+G$40)^5+'Unlevered FCF'!J$14/(1+G$40)^6)+('Unlevered FCF'!J$14*(1+$A41)/(G$40-$A41))/(1+G$40)^6-'Control Panel'!$B$85-'Control Panel'!$B$87-'Control Panel'!$B$88+'Control Panel'!$B$89+'Control Panel'!$B$90)/'Control Panel'!$B$86/'Control Panel'!$B$12-1 -> -0.22063656 | H41: =(('Unlevered FCF'!E$14/(1+H$40)^1+'Unlevered FCF'!F$14/(1+H$40)^2+'Unlevered FCF'!G$14/(1+H$40)^3+'Unlevered FCF'!H$14/(1+H$40)^4+'Unlevered FCF'!I$14/(1+H$40)^5+'Unlevered FCF'!J$14/(1+H$40)^6)+('Unlevered FCF'!J$14*(1+$A41)/(H$40-$A41))/(1+H$40)^6-'Control Panel'!$B$85-'Control Panel'!$B$87-'Control Panel'!$B$88+'Control Panel'!$B$89+'Control Panel'!$B$90)/'Control Panel'!$B$86/'Control Panel'!$B$12-1 -> -0.2697532
A42: 0.02 | B42: =(('Unlevered FCF'!E$14/(1+B$40)^1+'Unlevered FCF'!F$14/(1+B$40)^2+'Unlevered FCF'!G$14/(1+B$40)^3+'Unlevered FCF'!H$14/(1+B$40)^4+'Unlevered FCF'!I$14/(1+B$40)^5+'Unlevered FCF'!J$14/(1+B$40)^6)+('Unlevered FCF'!J$14*(1+$A42)/(B$40-$A42))/(1+B$40)^6-'Control Panel'!$B$85-'Control Panel'!$B$87-'Control Panel'!$B$88+'Control Panel'!$B$89+'Control Panel'!$B$90)/'Control Panel'!$B$86/'Control Panel'!$B$12-1 -> 0.23787565 | C42: =(('Unlevered FCF'!E$14/(1+C$40)^1+'Unlevered FCF'!F$14/(1+C$40)^2+'Unlevered FCF'!G$14/(1+C$40)^3+'Unlevered FCF'!H$14/(1+C$40)^4+'Unlevered FCF'!I$14/(1+C$40)^5+'Unlevered FCF'!J$14/(1+C$40)^6)+('Unlevered FCF'!J$14*(1+$A42)/(C$40-$A42))/(1+C$40)^6-'Control Panel'!$B$85-'Control Panel'!$B$87-'Control Panel'!$B$88+'Control Panel'!$B$89+'Control Panel'!$B$90)/'Control Panel'!$B$86/'Control Panel'!$B$12-1 -> 0.12534282 | D42: =(('Unlevered FCF'!E$14/(1+D$40)^1+'Unlevered FCF'!F$14/(1+D$40)^2+'Unlevered FCF'!G$14/(1+D$40)^3+'Unlevered FCF'!H$14/(1+D$40)^4+'Unlevered FCF'!I$14/(1+D$40)^5+'Unlevered FCF'!J$14/(1+D$40)^6)+('Unlevered FCF'!J$14*(1+$A42)/(D$40-$A42))/(1+D$40)^6-'Control Panel'!$B$85-'Control Panel'!$B$87-'Control Panel'!$B$88+'Control Panel'!$B$89+'Control Panel'!$B$90)/'Control Panel'!$B$86/'Control Panel'!$B$12-1 -> 0.030291956 | E42: =(('Unlevered FCF'!E$14/(1+E$40)^1+'Unlevered FCF'!F$14/(1+E$40)^2+'Unlevered FCF'!G$14/(1+E$40)^3+'Unlevered FCF'!H$14/(1+E$40)^4+'Unlevered FCF'!I$14/(1+E$40)^5+'Unlevered FCF'!J$14/(1+E$40)^6)+('Unlevered FCF'!J$14*(1+$A42)/(E$40-$A42))/(1+E$40)^6-'Control Panel'!$B$85-'Control Panel'!$B$87-'Control Panel'!$B$88+'Control Panel'!$B$89+'Control Panel'!$B$90)/'Control Panel'!$B$86/'Control Panel'!$B$12-1 -> -0.051027293 | F42: =(('Unlevered FCF'!E$14/(1+F$40)^1+'Unlevered FCF'!F$14/(1+F$40)^2+'Unlevered FCF'!G$14/(1+F$40)^3+'Unlevered FCF'!H$14/(1+F$40)^4+'Unlevered FCF'!I$14/(1+F$40)^5+'Unlevered FCF'!J$14/(1+F$40)^6)+('Unlevered FCF'!J$14*(1+$A42)/(F$40-$A42))/(1+F$40)^6-'Control Panel'!$B$85-'Control Panel'!$B$87-'Control Panel'!$B$88+'Control Panel'!$B$89+'Control Panel'!$B$90)/'Control Panel'!$B$86/'Control Panel'!$B$12-1 -> -0.12136507 | G42: =(('Unlevered FCF'!E$14/(1+G$40)^1+'Unlevered FCF'!F$14/(1+G$40)^2+'Unlevered FCF'!G$14/(1+G$40)^3+'Unlevered FCF'!H$14/(1+G$40)^4+'Unlevered FCF'!I$14/(1+G$40)^5+'Unlevered FCF'!J$14/(1+G$40)^6)+('Unlevered FCF'!J$14*(1+$A42)/(G$40-$A42))/(1+G$40)^6-'Control Panel'!$B$85-'Control Panel'!$B$87-'Control Panel'!$B$88+'Control Panel'!$B$89+'Control Panel'!$B$90)/'Control Panel'!$B$86/'Control Panel'!$B$12-1 -> -0.18278385 | H42: =(('Unlevered FCF'!E$14/(1+H$40)^1+'Unlevered FCF'!F$14/(1+H$40)^2+'Unlevered FCF'!G$14/(1+H$40)^3+'Unlevered FCF'!H$14/(1+H$40)^4+'Unlevered FCF'!I$14/(1+H$40)^5+'Unlevered FCF'!J$14/(1+H$40)^6)+('Unlevered FCF'!J$14*(1+$A42)/(H$40-$A42))/(1+H$40)^6-'Control Panel'!$B$85-'Control Panel'!$B$87-'Control Panel'!$B$88+'Control Panel'!$B$89+'Control Panel'!$B$90)/'Control Panel'!$B$86/'Control Panel'!$B$12-1 -> -0.23686073
A43: 0.025 | B43: =(('Unlevered FCF'!E$14/(1+B$40)^1+'Unlevered FCF'!F$14/(1+B$40)^2+'Unlevered FCF'!G$14/(1+B$40)^3+'Unlevered FCF'!H$14/(1+B$40)^4+'Unlevered FCF'!I$14/(1+B$40)^5+'Unlevered FCF'!J$14/(1+B$40)^6)+('Unlevered FCF'!J$14*(1+$A43)/(B$40-$A43))/(1+B$40)^6-'Control Panel'!$B$85-'Control Panel'!$B$87-'Control Panel'!$B$88+'Control Panel'!$B$89+'Control Panel'!$B$90)/'Control Panel'!$B$86/'Control Panel'!$B$12-1 -> 0.34287685 | C43: =(('Unlevered FCF'!E$14/(1+C$40)^1+'Unlevered FCF'!F$14/(1+C$40)^2+'Unlevered FCF'!G$14/(1+C$40)^3+'Unlevered FCF'!H$14/(1+C$40)^4+'Unlevered FCF'!I$14/(1+C$40)^5+'Unlevered FCF'!J$14/(1+C$40)^6)+('Unlevered FCF'!J$14*(1+$A43)/(C$40-$A43))/(1+C$40)^6-'Control Panel'!$B$85-'Control Panel'!$B$87-'Control Panel'!$B$88+'Control Panel'!$B$89+'Control Panel'!$B$90)/'Control Panel'!$B$86/'Control Panel'!$B$12-1 -> 0.210837 | D43: =(('Unlevered FCF'!E$14/(1+D$40)^1+'Unlevered FCF'!F$14/(1+D$40)^2+'Unlevered FCF'!G$14/(1+D$40)^3+'Unlevered FCF'!H$14/(1+D$40)^4+'Unlevered FCF'!I$14/(1+D$40)^5+'Unlevered FCF'!J$14/(1+D$40)^6)+('Unlevered FCF'!J$14*(1+$A43)/(D$40-$A43))/(1+D$40)^6-'Control Panel'!$B$85-'Control Panel'!$B$87-'Control Panel'!$B$88+'Control Panel'!$B$89+'Control Panel'!$B$90)/'Control Panel'!$B$86/'Control Panel'!$B$12-1 -> 0.10098163 | E43: =(('Unlevered FCF'!E$14/(1+E$40)^1+'Unlevered FCF'!F$14/(1+E$40)^2+'Unlevered FCF'!G$14/(1+E$40)^3+'Unlevered FCF'!H$14/(1+E$40)^4+'Unlevered FCF'!I$14/(1+E$40)^5+'Unlevered FCF'!J$14/(1+E$40)^6)+('Unlevered FCF'!J$14*(1+$A43)/(E$40-$A43))/(1+E$40)^6-'Control Panel'!$B$85-'Control Panel'!$B$87-'Control Panel'!$B$88+'Control Panel'!$B$89+'Control Panel'!$B$90)/'Control Panel'!$B$86/'Control Panel'!$B$12-1 -> 0.0081868456 | F43: =(('Unlevered FCF'!E$14/(1+F$40)^1+'Unlevered FCF'!F$14/(1+F$40)^2+'Unlevered FCF'!G$14/(1+F$40)^3+'Unlevered FCF'!H$14/(1+F$40)^4+'Unlevered FCF'!I$14/(1+F$40)^5+'Unlevered FCF'!J$14/(1+F$40)^6)+('Unlevered FCF'!J$14*(1+$A43)/(F$40-$A43))/(1+F$40)^6-'Control Panel'!$B$85-'Control Panel'!$B$87-'Control Panel'!$B$88+'Control Panel'!$B$89+'Control Panel'!$B$90)/'Control Panel'!$B$86/'Control Panel'!$B$12-1 -> -0.071207159 | G43: =(('Unlevered FCF'!E$14/(1+G$40)^1+'Unlevered FCF'!F$14/(1+G$40)^2+'Unlevered FCF'!G$14/(1+G$40)^3+'Unlevered FCF'!H$14/(1+G$40)^4+'Unlevered FCF'!I$14/(1+G$40)^5+'Unlevered FCF'!J$14/(1+G$40)^6)+('Unlevered FCF'!J$14*(1+$A43)/(G$40-$A43))/(1+G$40)^6-'Control Panel'!$B$85-'Control Panel'!$B$87-'Control Panel'!$B$88+'Control Panel'!$B$89+'Control Panel'!$B$90)/'Control Panel'!$B$86/'Control Panel'!$B$12-1 -> -0.13988411 | H43: =(('Unlevered FCF'!E$14/(1+H$40)^1+'Unlevered FCF'!F$14/(1+H$40)^2+'Unlevered FCF'!G$14/(1+H$40)^3+'Unlevered FCF'!H$14/(1+H$40)^4+'Unlevered FCF'!I$14/(1+H$40)^5+'Unlevered FCF'!J$14/(1+H$40)^6)+('Unlevered FCF'!J$14*(1+$A43)/(H$40-$A43))/(1+H$40)^6-'Control Panel'!$B$85-'Control Panel'!$B$87-'Control Panel'!$B$88+'Control Panel'!$B$89+'Control Panel'!$B$90)/'Control Panel'!$B$86/'Control Panel'!$B$12-1 -> -0.19985671
A44: 0.03 | B44: =(('Unlevered FCF'!E$14/(1+B$40)^1+'Unlevered FCF'!F$14/(1+B$40)^2+'Unlevered FCF'!G$14/(1+B$40)^3+'Unlevered FCF'!H$14/(1+B$40)^4+'Unlevered FCF'!I$14/(1+B$40)^5+'Unlevered FCF'!J$14/(1+B$40)^6)+('Unlevered FCF'!J$14*(1+$A44)/(B$40-$A44))/(1+B$40)^6-'Control Panel'!$B$85-'Control Panel'!$B$87-'Control Panel'!$B$88+'Control Panel'!$B$89+'Control Panel'!$B$90)/'Control Panel'!$B$86/'Control Panel'!$B$12-1 -> 0.47121166 | C44: =(('Unlevered FCF'!E$14/(1+C$40)^1+'Unlevered FCF'!F$14/(1+C$40)^2+'Unlevered FCF'!G$14/(1+C$40)^3+'Unlevered FCF'!H$14/(1+C$40)^4+'Unlevered FCF'!I$14/(1+C$40)^5+'Unlevered FCF'!J$14/(1+C$40)^6)+('Unlevered FCF'!J$14*(1+$A44)/(C$40-$A44))/(1+C$40)^6-'Control Panel'!$B$85-'Control Panel'!$B$87-'Control Panel'!$B$88+'Control Panel'!$B$89+'Control Panel'!$B$90)/'Control Panel'!$B$86/'Control Panel'!$B$12-1 -> 0.31343003 | D44: =(('Unlevered FCF'!E$14/(1+D$40)^1+'Unlevered FCF'!F$14/(1+D$40)^2+'Unlevered FCF'!G$14/(1+D$40)^3+'Unlevered FCF'!H$14/(1+D$40)^4+'Unlevered FCF'!I$14/(1+D$40)^5+'Unlevered FCF'!J$14/(1+D$40)^6)+('Unlevered FCF'!J$14*(1+$A44)/(D$40-$A44))/(1+D$40)^6-'Control Panel'!$B$85-'Control Panel'!$B$87-'Control Panel'!$B$88+'Control Panel'!$B$89+'Control Panel'!$B$90)/'Control Panel'!$B$86/'Control Panel'!$B$12-1 -> 0.18452398 | E44: =(('Unlevered FCF'!E$14/(1+E$40)^1+'Unlevered FCF'!F$14/(1+E$40)^2+'Unlevered FCF'!G$14/(1+E$40)^3+'Unlevered FCF'!H$14/(1+E$40)^4+'Unlevered FCF'!I$14/(1+E$40)^5+'Unlevered FCF'!J$14/(1+E$40)^6)+('Unlevered FCF'!J$14*(1+$A44)/(E$40-$A44))/(1+E$40)^6-'Control Panel'!$B$85-'Control Panel'!$B$87-'Control Panel'!$B$88+'Control Panel'!$B$89+'Control Panel'!$B$90)/'Control Panel'!$B$86/'Control Panel'!$B$12-1 -> 0.077270008 | F44: =(('Unlevered FCF'!E$14/(1+F$40)^1+'Unlevered FCF'!F$14/(1+F$40)^2+'Unlevered FCF'!G$14/(1+F$40)^3+'Unlevered FCF'!H$14/(1+F$40)^4+'Unlevered FCF'!I$14/(1+F$40)^5+'Unlevered FCF'!J$14/(1+F$40)^6)+('Unlevered FCF'!J$14*(1+$A44)/(F$40-$A44))/(1+F$40)^6-'Control Panel'!$B$85-'Control Panel'!$B$87-'Control Panel'!$B$88+'Control Panel'!$B$89+'Control Panel'!$B$90)/'Control Panel'!$B$86/'Control Panel'!$B$12-1 -> -0.013332651 | G44: =(('Unlevered FCF'!E$14/(1+G$40)^1+'Unlevered FCF'!F$14/(1+G$40)^2+'Unlevered FCF'!G$14/(1+G$40)^3+'Unlevered FCF'!H$14/(1+G$40)^4+'Unlevered FCF'!I$14/(1+G$40)^5+'Unlevered FCF'!J$14/(1+G$40)^6)+('Unlevered FCF'!J$14*(1+$A44)/(G$40-$A44))/(1+G$40)^6-'Control Panel'!$B$85-'Control Panel'!$B$87-'Control Panel'!$B$88+'Control Panel'!$B$89+'Control Panel'!$B$90)/'Control Panel'!$B$86/'Control Panel'!$B$12-1 -> -0.090855841 | H44: =(('Unlevered FCF'!E$14/(1+H$40)^1+'Unlevered FCF'!F$14/(1+H$40)^2+'Unlevered FCF'!G$14/(1+H$40)^3+'Unlevered FCF'!H$14/(1+H$40)^4+'Unlevered FCF'!I$14/(1+H$40)^5+'Unlevered FCF'!J$14/(1+H$40)^6)+('Unlevered FCF'!J$14*(1+$A44)/(H$40-$A44))/(1+H$40)^6-'Control Panel'!$B$85-'Control Panel'!$B$87-'Control Panel'!$B$88+'Control Panel'!$B$89+'Control Panel'!$B$90)/'Control Panel'!$B$86/'Control Panel'!$B$12-1 -> -0.15791881
A45: 0.035 | B45: =(('Unlevered FCF'!E$14/(1+B$40)^1+'Unlevered FCF'!F$14/(1+B$40)^2+'Unlevered FCF'!G$14/(1+B$40)^3+'Unlevered FCF'!H$14/(1+B$40)^4+'Unlevered FCF'!I$14/(1+B$40)^5+'Unlevered FCF'!J$14/(1+B$40)^6)+('Unlevered FCF'!J$14*(1+$A45)/(B$40-$A45))/(1+B$40)^6-'Control Panel'!$B$85-'Control Panel'!$B$87-'Control Panel'!$B$88+'Control Panel'!$B$89+'Control Panel'!$B$90)/'Control Panel'!$B$86/'Control Panel'!$B$12-1 -> 0.63163017 | C45: =(('Unlevered FCF'!E$14/(1+C$40)^1+'Unlevered FCF'!F$14/(1+C$40)^2+'Unlevered FCF'!G$14/(1+C$40)^3+'Unlevered FCF'!H$14/(1+C$40)^4+'Unlevered FCF'!I$14/(1+C$40)^5+'Unlevered FCF'!J$14/(1+C$40)^6)+('Unlevered FCF'!J$14*(1+$A45)/(C$40-$A45))/(1+C$40)^6-'Control Panel'!$B$85-'Control Panel'!$B$87-'Control Panel'!$B$88+'Control Panel'!$B$89+'Control Panel'!$B$90)/'Control Panel'!$B$86/'Control Panel'!$B$12-1 -> 0.4388215 | D45: =(('Unlevered FCF'!E$14/(1+D$40)^1+'Unlevered FCF'!F$14/(1+D$40)^2+'Unlevered FCF'!G$14/(1+D$40)^3+'Unlevered FCF'!H$14/(1+D$40)^4+'Unlevered FCF'!I$14/(1+D$40)^5+'Unlevered FCF'!J$14/(1+D$40)^6)+('Unlevered FCF'!J$14*(1+$A45)/(D$40-$A45))/(1+D$40)^6-'Control Panel'!$B$85-'Control Panel'!$B$87-'Control Panel'!$B$88+'Control Panel'!$B$89+'Control Panel'!$B$90)/'Control Panel'!$B$86/'Control Panel'!$B$12-1 -> 0.2847748 | E45: =(('Unlevered FCF'!E$14/(1+E$40)^1+'Unlevered FCF'!F$14/(1+E$40)^2+'Unlevered FCF'!G$14/(1+E$40)^3+'Unlevered FCF'!H$14/(1+E$40)^4+'Unlevered FCF'!I$14/(1+E$40)^5+'Unlevered FCF'!J$14/(1+E$40)^6)+('Unlevered FCF'!J$14*(1+$A45)/(E$40-$A45))/(1+E$40)^6-'Control Panel'!$B$85-'Control Panel'!$B$87-'Control Panel'!$B$88+'Control Panel'!$B$89+'Control Panel'!$B$90)/'Control Panel'!$B$86/'Control Panel'!$B$12-1 -> 0.15891374 | F45: =(('Unlevered FCF'!E$14/(1+F$40)^1+'Unlevered FCF'!F$14/(1+F$40)^2+'Unlevered FCF'!G$14/(1+F$40)^3+'Unlevered FCF'!H$14/(1+F$40)^4+'Unlevered FCF'!I$14/(1+F$40)^5+'Unlevered FCF'!J$14/(1+F$40)^6)+('Unlevered FCF'!J$14*(1+$A45)/(F$40-$A45))/(1+F$40)^6-'Control Panel'!$B$85-'Control Panel'!$B$87-'Control Panel'!$B$88+'Control Panel'!$B$89+'Control Panel'!$B$90)/'Control Panel'!$B$86/'Control Panel'!$B$12-1 -> 0.054187608 | G45: =(('Unlevered FCF'!E$14/(1+G$40)^1+'Unlevered FCF'!F$14/(1+G$40)^2+'Unlevered FCF'!G$14/(1+G$40)^3+'Unlevered FCF'!H$14/(1+G$40)^4+'Unlevered FCF'!I$14/(1+G$40)^5+'Unlevered FCF'!J$14/(1+G$40)^6)+('Unlevered FCF'!J$14*(1+$A45)/(G$40-$A45))/(1+G$40)^6-'Control Panel'!$B$85-'Control Panel'!$B$87-'Control Panel'!$B$88+'Control Panel'!$B$89+'Control Panel'!$B$90)/'Control Panel'!$B$86/'Control Panel'!$B$12-1 -> -0.034284759 | H45: =(('Unlevered FCF'!E$14/(1+H$40)^1+'Unlevered FCF'!F$14/(1+H$40)^2+'Unlevered FCF'!G$14/(1+H$40)^3+'Unlevered FCF'!H$14/(1+H$40)^4+'Unlevered FCF'!I$14/(1+H$40)^5+'Unlevered FCF'!J$14/(1+H$40)^6)+('Unlevered FCF'!J$14*(1+$A45)/(H$40-$A45))/(1+H$40)^6-'Control Panel'!$B$85-'Control Panel'!$B$87-'Control Panel'!$B$88+'Control Panel'!$B$89+'Control Panel'!$B$90)/'Control Panel'!$B$86/'Control Panel'!$B$12-1 -> -0.10998978
A48: Base / downside / upside case matrix
A49: Case | B49: Revenue CAGR | C49: Terminal EBITDA margin | D49: WACC | E49: Terminal growth | F49: Exit multiple | G49: Implied share price | H49: Upside / downside
A50: Downside | B50: =INDEX('Control Panel'!G$21:G$23,MATCH(A50,'Control Panel'!$A$21:$A$23,0)) -> 0.06 | C50: =INDEX('Control Panel'!G$26:G$28,MATCH(A50,'Control Panel'!$A$26:$A$28,0)) -> 0.25 | D50: ='Control Panel'!$B$78 -> 0.0862765 | E50: ='Control Panel'!$B$83 -> 0.03 | F50: ='Control Panel'!$B$84 -> 15 | G50: =G70 -> 65.091441 | H50: =G50/'Control Panel'!$B$12-1 -> -0.33136681
A51: Base | B51: =INDEX('Control Panel'!G$21:G$23,MATCH(A51,'Control Panel'!$A$21:$A$23,0)) -> 0.12 | C51: =INDEX('Control Panel'!G$26:G$28,MATCH(A51,'Control Panel'!$A$26:$A$28,0)) -> 0.31 | D51: ='Control Panel'!$B$78 -> 0.0862765 | E51: ='Control Panel'!$B$83 -> 0.03 | F51: ='Control Panel'!$B$84 -> 15 | G51: ='DCF Valuation'!$B$18*(1+(B51-B51)*2+(C51-C51)*3) -> 112.46977 | H51: =G51/'Control Panel'!$B$12-1 -> 0.15531353
A52: Upside | B52: =INDEX('Control Panel'!G$21:G$23,MATCH(A52,'Control Panel'!$A$21:$A$23,0)) -> 0.15 | C52: =INDEX('Control Panel'!G$26:G$28,MATCH(A52,'Control Panel'!$A$26:$A$28,0)) -> 0.36 | D52: ='Control Panel'!$B$78 -> 0.0862765 | E52: ='Control Panel'!$B$83 -> 0.03 | F52: ='Control Panel'!$B$84 -> 15 | G52: =N70 -> 147.69919 | H52: =G52/'Control Panel'!$B$12-1 -> 0.51719761
B56: ='Historical Financials'!$D$6*(1+'Control Panel'!B$22) -> 16209.782 | C56: =B56*(1+'Control Panel'!C$22) -> 18965.445 | D56: =C56*(1+'Control Panel'!D$22) -> 21620.608 | E56: =D56*(1+'Control Panel'!E$22) -> 23998.875 | F56: =E56*(1+'Control Panel'!F$22) -> 25918.785 | G56: =F56*(1+'Control Panel'!G$22) -> 27473.912 | I56: ='Historical Financials'!$D$6*(1+'Control Panel'!B$23) -> 16209.782 | J56: =I56*(1+'Control Panel'!C$23) -> 19775.935 | K56: =J56*(1+'Control Panel'!D$23) -> 23928.881 | L56: =K56*(1+'Control Panel'!E$23) -> 28475.368 | M56: =L56*(1+'Control Panel'!F$23) -> 33316.181 | N56: =M56*(1+'Control Panel'!G$23) -> 38313.608
B57: =B56*'Control Panel'!B$32 -> 2674.6141 | C57: =C56*'Control Panel'!C$32 -> 3034.4713 | D57: =D56*'Control Panel'!D$32 -> 3675.5033 | E57: =E56*'Control Panel'!E$32 -> 4319.7974 | F57: =F56*'Control Panel'!F$32 -> 4924.5691 | G57: =G56*'Control Panel'!G$32 -> 5494.7823 | I57: =I56*'Control Panel'!B$33 -> 2674.6141 | J57: =J56*'Control Panel'!C$33 -> 3955.1869 | K57: =K56*'Control Panel'!D$33 -> 5503.6426 | L57: =L56*'Control Panel'!E$33 -> 7403.5957 | M57: =M56*'Control Panel'!F$33 -> 9661.6924 | N57: =N56*'Control Panel'!G$33 -> 11877.218
B58: =B57*'Control Panel'!B$57 -> 561.66896 | C58: =C57*'Control Panel'!C$57 -> 637.23897 | D58: =D57*'Control Panel'!D$57 -> 771.8557 | E58: =E57*'Control Panel'!E$57 -> 907.15746 | F58: =F57*'Control Panel'!F$57 -> 1034.1595 | G58: =G57*'Control Panel'!G$57 -> 1153.9043 | I58: =I57*'Control Panel'!B$58 -> 561.66896 | J58: =J57*'Control Panel'!C$58 -> 830.58925 | K58: =K57*'Control Panel'!D$58 -> 1155.7649 | L58: =L57*'Control Panel'!E$58 -> 1554.7551 | M58: =M57*'Control Panel'!F$58 -> 2028.9554 | N58: =N57*'Control Panel'!G$58 -> 2494.2159
B59: =B56*'Control Panel'!B$37 -> 810.48912 | C59: =C56*'Control Panel'!C$37 -> 948.27227 | D59: =D56*'Control Panel'!D$37 -> 1081.0304 | E59: =E56*'Control Panel'!E$37 -> 1199.9437 | F59: =F56*'Control Panel'!F$37 -> 1295.9392 | G59: =G56*'Control Panel'!G$37 -> 1373.6956 | I59: =I56*'Control Panel'!B$38 -> 810.48912 | J59: =J56*'Control Panel'!C$38 -> 988.79673 | K59: =K56*'Control Panel'!D$38 -> 1196.444 | L59: =L56*'Control Panel'!E$38 -> 1423.7684 | M59: =M56*'Control Panel'!F$38 -> 1665.809 | N59: =N56*'Control Panel'!G$38 -> 1915.6804
B60: =B56*'Control Panel'!B$42 -> 972.58694 | C60: =C56*'Control Panel'!C$42 -> 1137.9267 | D60: =D56*'Control Panel'!D$42 -> 1297.2365 | E60: =E56*'Control Panel'!E$42 -> 1439.9325 | F60: =F56*'Control Panel'!F$42 -> 1555.1271 | G60: =G56*'Control Panel'!G$42 -> 1648.4347 | I60: =I56*'Control Panel'!B$43 -> 972.58694 | J60: =J56*'Control Panel'!C$43 -> 1186.5561 | K60: =K56*'Control Panel'!D$43 -> 1435.7328 | L60: =L56*'Control Panel'!E$43 -> 1708.5221 | M60: =M56*'Control Panel'!F$43 -> 1998.9708 | N60: =N56*'Control Panel'!G$43 -> 2298.8165
B61: =B56*'Control Panel'!B$47 -> -6321.8151 | C61: =C56*'Control Panel'!C$47 -> -6827.5603 | D61: =D56*'Control Panel'!D$47 -> -7783.4188 | E61: =E56*'Control Panel'!E$47 -> -8639.5949 | F61: =F56*'Control Panel'!F$47 -> -9330.7625 | G61: =G56*'Control Panel'!G$47 -> -9890.6082 | I61: =I56*'Control Panel'!B$48 -> -6321.8151 | J61: =J56*'Control Panel'!C$48 -> -8305.8925 | K61: =K56*'Control Panel'!D$48 -> -10050.13 | L61: =L56*'Control Panel'!E$48 -> -11959.655 | M61: =M56*'Control Panel'!F$48 -> -13992.796 | N61: =N56*'Control Panel'!G$48 -> -16091.715
B62: =B61-'Historical Financials'!$D$18 -> -1171.8151 | C62: =C61-B61 -> -505.74521 | D62: =D61-C61 -> -955.85845 | E62: =E61-D61 -> -856.17607 | F62: =F61-E61 -> -691.16759 | G62: =G61-F61 -> -559.84575 | I62: =I61-'Historical Financials'!$D$18 -> -1171.8151 | J62: =J61-I61 -> -1984.0774 | K62: =K61-J61 -> -1744.2374 | L62: =L61-K61 -> -1909.5247 | M62: =M61-L61 -> -2033.1413 | N62: =N61-M61 -> -2098.9194
B63: =B57-B58+B59-B60-B62 -> 3122.6624 | C63: =C57-C58+C59-C60-C62 -> 2713.3231 | D63: =D57-D58+D59-D60-D62 -> 3643.3 | E63: =E57-E58+E59-E60-E62 -> 4028.8273 | F63: =F57-F58+F59-F60-F62 -> 4322.3893 | G63: =G57-G58+G59-G60-G62 -> 4625.9847 | I63: =I57-I58+I59-I60-I62 -> 3122.6624 | J63: =J57-J58+J59-J60-J62 -> 4910.9157 | K63: =K57-K58+K59-K60-K62 -> 5852.8263 | L63: =L57-L58+L59-L60-L62 -> 7473.6116 | M63: =M57-M58+M59-M60-M62 -> 9332.7165 | N63: =N57-N58+N59-N60-N62 -> 11098.786
B64: =1/(1+'Control Panel'!$B$78)^1 -> 0.92057593 | C64: =1/(1+'Control Panel'!$B$78)^2 -> 0.84746004 | D64: =1/(1+'Control Panel'!$B$78)^3 -> 0.78015132 | E64: =1/(1+'Control Panel'!$B$78)^4 -> 0.71818853 | F64: =1/(1+'Control Panel'!$B$78)^5 -> 0.66114707 | G64: =1/(1+'Control Panel'!$B$78)^6 -> 0.60863608 | I64: =1/(1+'Control Panel'!$B$78)^1 -> 0.92057593 | J64: =1/(1+'Control Panel'!$B$78)^2 -> 0.84746004 | K64: =1/(1+'Control Panel'!$B$78)^3 -> 0.78015132 | L64: =1/(1+'Control Panel'!$B$78)^4 -> 0.71818853 | M64: =1/(1+'Control Panel'!$B$78)^5 -> 0.66114707 | N64: =1/(1+'Control Panel'!$B$78)^6 -> 0.60863608
B65: =B63*B64 -> 2874.6479 | C65: =C63*C64 -> 2299.4329 | D65: =D63*D64 -> 2842.3253 | E65: =E63*E64 -> 2893.4575 | F65: =F63*F64 -> 2857.735 | G65: =G63*G64 -> 2815.5412 | I65: =I63*I64 -> 2874.6479 | J65: =J63*J64 -> 4161.8048 | K65: =K63*K64 -> 4566.0901 | L65: =L63*L64 -> 5367.4621 | M65: =M63*M64 -> 6170.2982 | N65: =N63*N64 -> 6755.1215
G66: =G63*(1+'Control Panel'!$B$83)/('Control Panel'!$B$78-'Control Panel'!$B$83) -> 84667.032 | N66: =N63*(1+'Control Panel'!$B$83)/('Control Panel'!$B$78-'Control Panel'!$B$83) -> 203135.4
G67: =G66*G64 -> 51531.41 | N67: =N66*N64 -> 123635.53
G68: =SUM(B65:G65)+G67 -> 68114.55 | N68: =SUM(I65:N65)+N67 -> 153530.96
G69: =G68-'Control Panel'!$B$85 -> 67304.55 | N69: =N68-'Control Panel'!$B$85 -> 152720.96
G70: =G69/'Control Panel'!$B$86 -> 65.091441 | N70: =N69/'Control Panel'!$B$86 -> 147.69919

Sheet Checks
A1: Model Integrity Checks
A4: Check | B4: Formula / tie-out | C4: Status | D4: Notes | E4: Severity | F4: Owner
A5: Revenue forecast ties | B5: =ABS('Revenue Build'!J$14-'Margin Cost Build'!J$8) -> 0 | C5: =IF(B5<0.1,"OK","FAIL") -> OK | D5: Revenue Build output ties to Margin Cost Build | E5: Hard failure | F5: Model owner
A6: EBITDA ties | B6: =ABS('Margin Cost Build'!J$12-('Margin Cost Build'!J$8*'Margin Cost Build'!J$11)) -> 0 | C6: =IF(B6<0.1,"OK","FAIL") -> OK | D6: EBITDA equals revenue times EBITDA margin | E6: Hard failure | F6: Model owner
A7: D&A ties to Capex / D&A tab | B7: =ABS('Margin Cost Build'!J$13-'Capex D&A'!J$12) -> 0 | C7: =IF(B7<0.1,"OK","FAIL") -> OK | D7: D&A ties to Capex / D&A tab | E7: Hard failure | F7: Model owner
A8: Change in NWC ties | B8: =ABS('Unlevered FCF'!J$13-'Working Capital'!J$17) -> 0 | C8: =IF(B8<0.1,"OK","FAIL") -> OK | D8: Change in NWC ties to Working Capital | E8: Hard failure | F8: Model owner
A9: Unlevered FCF ties | B9: =ABS('Unlevered FCF'!J$14-('Unlevered FCF'!J$10+'Unlevered FCF'!J$11-'Unlevered FCF'!J$12-'Unlevered FCF'!J$13)) -> 0 | C9: =IF(B9<0.1,"OK","FAIL") -> OK | D9: FCF formula integrity | E9: Hard failure | F9: Model owner
A10: Discount factors are positive | B10: =MIN('Unlevered FCF'!E$16:J$16) -> 0.60863608 | C10: =IF(B10>0,"OK","FAIL") -> OK | D10: Discount factors must be positive | E10: Hard failure | F10: Model owner
A11: Terminal value is positive | B11: ='Terminal Value'!B$12 -> 152744.63 | C11: =IF(B11>0,"OK","FAIL") -> OK | D11: Selected terminal value must be positive | E11: Hard failure | F11: Model owner
A12: Enterprise value equals PV FCF + PV terminal value | B12: =ABS('DCF Valuation'!B$6-('DCF Valuation'!B$4+'DCF Valuation'!B$5)) -> 0 | C12: =IF(B12<0.1,"OK","FAIL") -> OK | D12: Enterprise value ties | E12: Hard failure | F12: Model owner
A13: Equity bridge ties | B13: =ABS('DCF Valuation'!B$16-('DCF Valuation'!B$6-'DCF Valuation'!B$11-'DCF Valuation'!B$12-'DCF Valuation'!B$13+'DCF Valuation'!B$14+'DCF Valuation'!B$15)) -> 0 | C13: =IF(B13<0.1,"OK","FAIL") -> OK | D13: EV-to-equity bridge ties | E13: Hard failure | F13: Model owner
A14: Share price calculation ties | B14: =ABS('DCF Valuation'!B$18-'DCF Valuation'!B$16/'DCF Valuation'!B$17) -> 0 | C14: =IF(B14<0.01,"OK","FAIL") -> OK | D14: Implied share price ties | E14: Hard failure | F14: Model owner
A15: No missing scenario selection | B15: ='Control Panel'!$B$10 -> Base | C15: =IF(OR(B15="Base",B15="Downside",B15="Upside"),"OK","FAIL") -> OK | D15: Scenario selection must be valid | E15: Hard failure | F15: Model owner
A16: No external links | B16: ='Control Panel'!$B$79 -> No external links | C16: =IF(B16="No external links","OK","FAIL") -> OK | D16: Validated by builder and tests | E16: Hard failure | F16: Model owner
A17: Formula directionality - WACC sensitivity | B17: =Sensitivities!B5-Sensitivities!H5 -> 40.899446 | C17: =IF(B17>0,"OK","FAIL") -> OK | D17: Share price should decrease as WACC increases | E17: Warning | F17: Model owner
A18: Terminal growth directionality | B18: =Sensitivities!B9-Sensitivities!B5 -> 46.850226 | C18: =IF(B18>0,"OK","FAIL") -> OK | D18: Share price should increase as terminal growth increases | E18: Warning | F18: Model owner
A19: Diluted shares positive | B19: ='Control Panel'!$B$86 -> 1034 | C19: =IF(B19>0,"OK","FAIL") -> OK | D19: Share count must be positive | E19: Hard failure | F19: Model owner
A20: WACC greater than terminal growth | B20: ='Control Panel'!$B$78-'Control Panel'!$B$83 -> 0.0562765 | C20: =IF(B20>0,"OK","FAIL") -> OK | D20: Gordon growth requires WACC > g | E20: Hard failure | F20: Model owner
A21: Ending PP&E non-negative when roll-forward modeled | B21: =IF(COUNT('Capex D&A'!E13:J13)=0,"Not modeled",MIN('Capex D&A'!E13:J13)) -> 2451.0978 | C21: =IF(B21="Not modeled","OPEN",IF(B21>=0,"OK","FAIL")) -> OK | D21: A source-backed PP&E roll-forward must not project negative assets | E21: Hard failure when modeled | F21: Model owner
A22: Source labels present | B22: =COUNTA('Source Notes'!C6:C13) -> 7 | C22: =IF(B22>=5,"OK","FAIL") -> OK | D22: Source notes and confidence labels are required | E22: Hard failure | F22: Model owner

Sheet Source Notes
A1: Source Notes and Evidence Tracking
A4: Input area | B4: Source | C4: Evidence label | D4: As-of date | E4: Confidence | F4: Notes / diligence items | G4: Owner | H4: Status
A5: Historical financials | B5: ServiceNow FY2025 Form 10-K | C5: derived | D5: 2025-12-31 | E5: High | F5: Revenue, non-GAAP operating income, SBC, D&A, capex, cash flow, deferred revenue, and other working-capital inputs are from the filing. Owner FCFF treats SBC as an economic expense. https://www.sec.gov/Archives/edgar/data/1373715/000137371526000007/now-20251231.htm | G5: Model owner | H5: Reviewed
A6: Forecast assumptions | B6: Analyst operating cases anchored to ServiceNow Q2 2026 results, FY2026 guidance, and 2030 targets | C6: analyst_estimate | D6: 2026-07-23 | E6: Medium | F6: No consensus estimates are used. Revenue growth is anchored to Q2 cRPO growth, FY2026 subscription guidance, and the company's $30bn+ 2030 subscription revenue target. Margin cases deduct SBC as an economic cost. https://investor.servicenow.com/news/news-details/2026/ServiceNow-Reports-Second-Quarter-2026-Financial-Results/default.aspx | G6: Model owner | H6: Open
A7: WACC assumptions | B7: 10-year Treasury, observed beta, and analyst ERP/company-risk assumptions | C7: derived | D7: 2026-07-23 | E7: Medium | F7: Risk-free rate is the 10-year Treasury yield; beta is a current public market-data observation. ERP and company-specific premium are analyst assumptions. https://home.treasury.gov/resource-center/data-chart-center/interest-rates/TextView?field_tdr_date_value=2026&type=daily_treasury_yield_curve ; https://stockanalysis.com/stocks/now/ | G7: Model owner | H7: Reviewed
A8: Terminal value | B8: Analyst long-run nominal growth framework | C8: analyst_estimate | D8: 2026-07-23 | E8: Medium | F8: Perpetual growth is scenario-based and remains below the scenario discount rate. The sensitivity grid shows the concentration of value in terminal assumptions. | G8: Model owner | H8: Open
A9: Net debt | B9: ServiceNow Q2 2026 earnings release balance sheet | C9: reported | D9: 2026-06-30 | E9: High | F9: Cash plus current and long-term marketable securities is $6,707mm; short- and long-term debt is $7,517mm. Strategic investments are excluded from the bridge. https://investor.servicenow.com/news/news-details/2026/ServiceNow-Reports-Second-Quarter-2026-Financial-Results/default.aspx | G9: Model owner | H9: Reviewed
A10: Diluted shares | B10: ServiceNow Q2 2026 earnings release | C10: reported | D10: 2026-06-30 | E10: High | F10: Q2 2026 diluted weighted-average shares were 1,034mm after the five-for-one split. https://investor.servicenow.com/news/news-details/2026/ServiceNow-Reports-Second-Quarter-2026-Financial-Results/default.aspx | G10: Model owner | H10: Reviewed
A11: Current share price | B11: NOW real-time market snapshot | C11: web_research | D11: 2026-07-23 | E11: Medium | F11: Observed share price was $97.35 at 10:12 a.m. EDT on July 23, 2026. This short-lived market-data input is used only for comparison and the reverse DCF. https://stockanalysis.com/stocks/now/ | G11: Model owner | H11: Reviewed
A12: Segment assumptions | B12: Plan schema | C12: derived | D12: 2026-07-23 | E12: Medium | F12: Forecast begins from total revenue unless a sector-relevant operating-driver schedule is provided; disclose any KPI proxy used for valuation. | G12: Model owner | H12: Open
